{
  "id" : "4dd74778-b92b-4632-af2a-6ef21803b721-209",
  "modifiedDate" : 1479411000192,
  "name" : "3879.txt",
  "version" : 3,
  "text" : "\r*José de Castro Nunes* nasceu em Campos (RJ) no dia 15 de outubro de\r1882, filho de João Francisco Leite Nunes e de Teresa da Conceição\rCastro Nunes.\r\rFez os primeiros estudos em sua cidade natal e no Colégio Pedro II, no\rRio de Janeiro, então Distrito Federal, ingressando posteriormente na\rFaculdade de Ciências Jurídicas e Sociais da capital federal. Ainda\restudante, exerceu o magistério, tendo lecionado física e regido o curso\rde matemática elementar do Liceu Literário Português. Bacharelou-se em\r1906.\r\rRedator do jornal Correio da Manhã, no Rio de Janeiro, e cronista\rjudiciário de 1906 a 1910, já em 1909 tornou-se também inspetor de\reducação, função que exerceria até 1911. No ano seguinte passou a\rredator do jornal carioca *A Noite*, do qual se desligou em 1915 para\ratuar como advogado municipal em Niterói na qualidade de procurador dos\rFeitos. Exerceu essa função até 1931 e, durante esse período, ocupou\rtambém o cargo de diretor da Caixa Econômica Federal no Rio de Janeiro\rentre maio de 1927 e janeiro de 1928, quando se tornou vice-presidente\rda instituição.\r\rApós a Revolução de 1930, atuou como juiz federal substituto na seção do\restado do Rio de Janeiro de 1931 a 1934. Nesse mesmo tempo integrou, em\r1932, a comissão encarregada de elaborar o anteprojeto de Constituição\rapresentado à Assembléia Nacional Constituinte em novembro de 1933. No\rano seguinte passou a juiz federal na 2ª Vara da seção do Distrito\rFederal, exercendo essa função até 1937. Tornou-se então juiz da 2ª Vara\rdos Feitos da Fazenda Pública no Distrito Federal, cargo que ocupou até\r1938.\r\rDurante o Estado Novo (1937-1945), atuou como membro do Tribunal de\rContas da União (TCU) no período de 1938 a 1940, sendo nomeado neste\rúltimo ano ministro do Supremo Tribunal Federal (STF). Presidente\rinterino (1945-1946) e vice-presidente (1945-1949) dessa corte, em maio\rde 1947 votou contra o *habeas-corpus* requerido por dirigentes comunistas\rsob a alegação de que estavam impedidos de entrar e sair da sede central\re dos comitês locais do Partido Comunista Brasileiro, então Partido\rComunista do Brasil (PCB). A decisão negativa foi tomada pelo STF por\runanimidade. Castro Nunes deixou o STF em setembro de 1949.\r\rJornalista, colaborou ainda na *Gazeta Judiciária*, em 1953, e no *Jornal\rdo Comércio*, do Rio de Janeiro.\r\rSócio da Academia Fluminense de Letras e do Instituto dos Advogados\rBrasileiros, integrou o conselho administrativo da Caixa Econômica\rFederal e o Conselho Penitenciário do Estado do Rio de Janeiro.\r\rFaleceu no Rio de Janeiro no dia 5 de setembro de 1959.\r\rPublicou *Do Estado federado e sua organização municipal* (1920), *As\rconstituições estaduais do Brasil comentadas e comparadas entre si e com\ra Constituição Federal* (1922), *A jornada revisionista* (1924), *Do mandado\rde segurança e de outros meios de defesa contra atos de poder público*\r(1937), *Teoria e prática do Poder Judiciário* (1943), *Soluções de direito\raplicado* (1953), *Alguns homens de meu tempo* (1957), *Bitributação e\rcompetência jurídica* e *Fazenda pública em juízo*.\r\r",
  "docLength" : 3065,
  "language" : "PT",
  "status" : "READY",
  "documentSet" : [ ],
  "preannotation" : [ "PRE_LW" ],
  "sentences" : [ {
    "id" : "s0",
    "begin" : 1,
    "end" : 150,
    "text" : "*José de Castro Nunes* nasceu em Campos (RJ) no dia 15 de outubro de\r1882, filho de João Francisco Leite Nunes e de Teresa da Conceição\rCastro Nunes.",
    "tokens" : [ {
      "id" : "s0-t0",
      "begin" : 1,
      "end" : 6,
      "text" : "*José",
      "whiteSpace" : false
    }, {
      "id" : "s0-t1",
      "begin" : 7,
      "end" : 9,
      "text" : "de",
      "whiteSpace" : false
    }, {
      "id" : "s0-t2",
      "begin" : 10,
      "end" : 16,
      "text" : "Castro",
      "whiteSpace" : false
    }, {
      "id" : "s0-t3",
      "begin" : 17,
      "end" : 22,
      "text" : "Nunes",
      "whiteSpace" : false
    }, {
      "id" : "s0-t4",
      "begin" : 22,
      "end" : 23,
      "text" : "*",
      "whiteSpace" : false
    }, {
      "id" : "s0-t5",
      "begin" : 24,
      "end" : 30,
      "text" : "nasceu",
      "whiteSpace" : false
    }, {
      "id" : "s0-t6",
      "begin" : 31,
      "end" : 33,
      "text" : "em",
      "whiteSpace" : false
    }, {
      "id" : "s0-t7",
      "begin" : 34,
      "end" : 40,
      "text" : "Campos",
      "whiteSpace" : false
    }, {
      "id" : "s0-t8",
      "begin" : 41,
      "end" : 42,
      "text" : "(",
      "whiteSpace" : false
    }, {
      "id" : "s0-t9",
      "begin" : 42,
      "end" : 44,
      "text" : "RJ",
      "whiteSpace" : false
    }, {
      "id" : "s0-t10",
      "begin" : 44,
      "end" : 45,
      "text" : ")",
      "whiteSpace" : false
    }, {
      "id" : "s0-t11",
      "begin" : 46,
      "end" : 48,
      "text" : "no",
      "whiteSpace" : false
    }, {
      "id" : "s0-t12",
      "begin" : 49,
      "end" : 52,
      "text" : "dia",
      "whiteSpace" : false
    }, {
      "id" : "s0-t13",
      "begin" : 53,
      "end" : 55,
      "text" : "15",
      "whiteSpace" : false
    }, {
      "id" : "s0-t14",
      "begin" : 56,
      "end" : 58,
      "text" : "de",
      "whiteSpace" : false
    }, {
      "id" : "s0-t15",
      "begin" : 59,
      "end" : 66,
      "text" : "outubro",
      "whiteSpace" : false
    }, {
      "id" : "s0-t16",
      "begin" : 67,
      "end" : 69,
      "text" : "de",
      "whiteSpace" : false
    }, {
      "id" : "s0-t17",
      "begin" : 70,
      "end" : 74,
      "text" : "1882",
      "whiteSpace" : false
    }, {
      "id" : "s0-t18",
      "begin" : 74,
      "end" : 75,
      "text" : ",",
      "whiteSpace" : false
    }, {
      "id" : "s0-t19",
      "begin" : 76,
      "end" : 81,
      "text" : "filho",
      "whiteSpace" : false
    }, {
      "id" : "s0-t20",
      "begin" : 82,
      "end" : 84,
      "text" : "de",
      "whiteSpace" : false
    }, {
      "id" : "s0-t21",
      "begin" : 85,
      "end" : 89,
      "text" : "João",
      "whiteSpace" : false
    }, {
      "id" : "s0-t22",
      "begin" : 90,
      "end" : 99,
      "text" : "Francisco",
      "whiteSpace" : false
    }, {
      "id" : "s0-t23",
      "begin" : 100,
      "end" : 105,
      "text" : "Leite",
      "whiteSpace" : false
    }, {
      "id" : "s0-t24",
      "begin" : 106,
      "end" : 111,
      "text" : "Nunes",
      "whiteSpace" : false
    }, {
      "id" : "s0-t25",
      "begin" : 112,
      "end" : 113,
      "text" : "e",
      "whiteSpace" : false
    }, {
      "id" : "s0-t26",
      "begin" : 114,
      "end" : 116,
      "text" : "de",
      "whiteSpace" : false
    }, {
      "id" : "s0-t27",
      "begin" : 117,
      "end" : 123,
      "text" : "Teresa",
      "whiteSpace" : false
    }, {
      "id" : "s0-t28",
      "begin" : 124,
      "end" : 126,
      "text" : "da",
      "whiteSpace" : false
    }, {
      "id" : "s0-t29",
      "begin" : 127,
      "end" : 136,
      "text" : "Conceição",
      "whiteSpace" : false
    }, {
      "id" : "s0-t30",
      "begin" : 137,
      "end" : 143,
      "text" : "Castro",
      "whiteSpace" : false
    }, {
      "id" : "s0-t31",
      "begin" : 144,
      "end" : 149,
      "text" : "Nunes",
      "whiteSpace" : false
    }, {
      "id" : "s0-t32",
      "begin" : 149,
      "end" : 150,
      "text" : ".",
      "whiteSpace" : false
    } ]
  }, {
    "id" : "s1",
    "begin" : 152,
    "end" : 354,
    "text" : "Fez os primeiros estudos em sua cidade natal e no Colégio Pedro II, no\rRio de Janeiro, então Distrito Federal, ingressando posteriormente na\rFaculdade de Ciências Jurídicas e Sociais da capital federal.",
    "tokens" : [ {
      "id" : "s1-t0",
      "begin" : 152,
      "end" : 155,
      "text" : "Fez",
      "whiteSpace" : false
    }, {
      "id" : "s1-t1",
      "begin" : 156,
      "end" : 158,
      "text" : "os",
      "whiteSpace" : false
    }, {
      "id" : "s1-t2",
      "begin" : 159,
      "end" : 168,
      "text" : "primeiros",
      "whiteSpace" : false
    }, {
      "id" : "s1-t3",
      "begin" : 169,
      "end" : 176,
      "text" : "estudos",
      "whiteSpace" : false
    }, {
      "id" : "s1-t4",
      "begin" : 177,
      "end" : 179,
      "text" : "em",
      "whiteSpace" : false
    }, {
      "id" : "s1-t5",
      "begin" : 180,
      "end" : 183,
      "text" : "sua",
      "whiteSpace" : false
    }, {
      "id" : "s1-t6",
      "begin" : 184,
      "end" : 190,
      "text" : "cidade",
      "whiteSpace" : false
    }, {
      "id" : "s1-t7",
      "begin" : 191,
      "end" : 196,
      "text" : "natal",
      "whiteSpace" : false
    }, {
      "id" : "s1-t8",
      "begin" : 197,
      "end" : 198,
      "text" : "e",
      "whiteSpace" : false
    }, {
      "id" : "s1-t9",
      "begin" : 199,
      "end" : 201,
      "text" : "no",
      "whiteSpace" : false
    }, {
      "id" : "s1-t10",
      "begin" : 202,
      "end" : 209,
      "text" : "Colégio",
      "whiteSpace" : false
    }, {
      "id" : "s1-t11",
      "begin" : 210,
      "end" : 215,
      "text" : "Pedro",
      "whiteSpace" : false
    }, {
      "id" : "s1-t12",
      "begin" : 216,
      "end" : 218,
      "text" : "II",
      "whiteSpace" : false
    }, {
      "id" : "s1-t13",
      "begin" : 218,
      "end" : 219,
      "text" : ",",
      "whiteSpace" : false
    }, {
      "id" : "s1-t14",
      "begin" : 220,
      "end" : 222,
      "text" : "no",
      "whiteSpace" : false
    }, {
      "id" : "s1-t15",
      "begin" : 223,
      "end" : 226,
      "text" : "Rio",
      "whiteSpace" : false
    }, {
      "id" : "s1-t16",
      "begin" : 227,
      "end" : 229,
      "text" : "de",
      "whiteSpace" : false
    }, {
      "id" : "s1-t17",
      "begin" : 230,
      "end" : 237,
      "text" : "Janeiro",
      "whiteSpace" : false
    }, {
      "id" : "s1-t18",
      "begin" : 237,
      "end" : 238,
      "text" : ",",
      "whiteSpace" : false
    }, {
      "id" : "s1-t19",
      "begin" : 239,
      "end" : 244,
      "text" : "então",
      "whiteSpace" : false
    }, {
      "id" : "s1-t20",
      "begin" : 245,
      "end" : 253,
      "text" : "Distrito",
      "whiteSpace" : false
    }, {
      "id" : "s1-t21",
      "begin" : 254,
      "end" : 261,
      "text" : "Federal",
      "whiteSpace" : false
    }, {
      "id" : "s1-t22",
      "begin" : 261,
      "end" : 262,
      "text" : ",",
      "whiteSpace" : false
    }, {
      "id" : "s1-t23",
      "begin" : 263,
      "end" : 274,
      "text" : "ingressando",
      "whiteSpace" : false
    }, {
      "id" : "s1-t24",
      "begin" : 275,
      "end" : 289,
      "text" : "posteriormente",
      "whiteSpace" : false
    }, {
      "id" : "s1-t25",
      "begin" : 290,
      "end" : 292,
      "text" : "na",
      "whiteSpace" : false
    }, {
      "id" : "s1-t26",
      "begin" : 293,
      "end" : 302,
      "text" : "Faculdade",
      "whiteSpace" : false
    }, {
      "id" : "s1-t27",
      "begin" : 303,
      "end" : 305,
      "text" : "de",
      "whiteSpace" : false
    }, {
      "id" : "s1-t28",
      "begin" : 306,
      "end" : 314,
      "text" : "Ciências",
      "whiteSpace" : false
    }, {
      "id" : "s1-t29",
      "begin" : 315,
      "end" : 324,
      "text" : "Jurídicas",
      "whiteSpace" : false
    }, {
      "id" : "s1-t30",
      "begin" : 325,
      "end" : 326,
      "text" : "e",
      "whiteSpace" : false
    }, {
      "id" : "s1-t31",
      "begin" : 327,
      "end" : 334,
      "text" : "Sociais",
      "whiteSpace" : false
    }, {
      "id" : "s1-t32",
      "begin" : 335,
      "end" : 337,
      "text" : "da",
      "whiteSpace" : false
    }, {
      "id" : "s1-t33",
      "begin" : 338,
      "end" : 345,
      "text" : "capital",
      "whiteSpace" : false
    }, {
      "id" : "s1-t34",
      "begin" : 346,
      "end" : 353,
      "text" : "federal",
      "whiteSpace" : false
    }, {
      "id" : "s1-t35",
      "begin" : 353,
      "end" : 354,
      "text" : ".",
      "whiteSpace" : false
    } ]
  }, {
    "id" : "s2",
    "begin" : 355,
    "end" : 487,
    "text" : "Ainda\restudante, exerceu o magistério, tendo lecionado física e regido o curso\rde matemática elementar do Liceu Literário Português.",
    "tokens" : [ {
      "id" : "s2-t0",
      "begin" : 355,
      "end" : 360,
      "text" : "Ainda",
      "whiteSpace" : false
    }, {
      "id" : "s2-t1",
      "begin" : 361,
      "end" : 370,
      "text" : "estudante",
      "whiteSpace" : false
    }, {
      "id" : "s2-t2",
      "begin" : 370,
      "end" : 371,
      "text" : ",",
      "whiteSpace" : false
    }, {
      "id" : "s2-t3",
      "begin" : 372,
      "end" : 379,
      "text" : "exerceu",
      "whiteSpace" : false
    }, {
      "id" : "s2-t4",
      "begin" : 380,
      "end" : 381,
      "text" : "o",
      "whiteSpace" : false
    }, {
      "id" : "s2-t5",
      "begin" : 382,
      "end" : 392,
      "text" : "magistério",
      "whiteSpace" : false
    }, {
      "id" : "s2-t6",
      "begin" : 392,
      "end" : 393,
      "text" : ",",
      "whiteSpace" : false
    }, {
      "id" : "s2-t7",
      "begin" : 394,
      "end" : 399,
      "text" : "tendo",
      "whiteSpace" : false
    }, {
      "id" : "s2-t8",
      "begin" : 400,
      "end" : 409,
      "text" : "lecionado",
      "whiteSpace" : false
    }, {
      "id" : "s2-t9",
      "begin" : 410,
      "end" : 416,
      "text" : "física",
      "whiteSpace" : false
    }, {
      "id" : "s2-t10",
      "begin" : 417,
      "end" : 418,
      "text" : "e",
      "whiteSpace" : false
    }, {
      "id" : "s2-t11",
      "begin" : 419,
      "end" : 425,
      "text" : "regido",
      "whiteSpace" : false
    }, {
      "id" : "s2-t12",
      "begin" : 426,
      "end" : 427,
      "text" : "o",
      "whiteSpace" : false
    }, {
      "id" : "s2-t13",
      "begin" : 428,
      "end" : 433,
      "text" : "curso",
      "whiteSpace" : false
    }, {
      "id" : "s2-t14",
      "begin" : 434,
      "end" : 436,
      "text" : "de",
      "whiteSpace" : false
    }, {
      "id" : "s2-t15",
      "begin" : 437,
      "end" : 447,
      "text" : "matemática",
      "whiteSpace" : false
    }, {
      "id" : "s2-t16",
      "begin" : 448,
      "end" : 457,
      "text" : "elementar",
      "whiteSpace" : false
    }, {
      "id" : "s2-t17",
      "begin" : 458,
      "end" : 460,
      "text" : "do",
      "whiteSpace" : false
    }, {
      "id" : "s2-t18",
      "begin" : 461,
      "end" : 466,
      "text" : "Liceu",
      "whiteSpace" : false
    }, {
      "id" : "s2-t19",
      "begin" : 467,
      "end" : 476,
      "text" : "Literário",
      "whiteSpace" : false
    }, {
      "id" : "s2-t20",
      "begin" : 477,
      "end" : 486,
      "text" : "Português",
      "whiteSpace" : false
    }, {
      "id" : "s2-t21",
      "begin" : 486,
      "end" : 487,
      "text" : ".",
      "whiteSpace" : false
    } ]
  }, {
    "id" : "s3",
    "begin" : 488,
    "end" : 510,
    "text" : "Bacharelou-se em\r1906.",
    "tokens" : [ {
      "id" : "s3-t0",
      "begin" : 488,
      "end" : 501,
      "text" : "Bacharelou-se",
      "whiteSpace" : false
    }, {
      "id" : "s3-t1",
      "begin" : 502,
      "end" : 504,
      "text" : "em",
      "whiteSpace" : false
    }, {
      "id" : "s3-t2",
      "begin" : 505,
      "end" : 509,
      "text" : "1906",
      "whiteSpace" : false
    }, {
      "id" : "s3-t3",
      "begin" : 509,
      "end" : 510,
      "text" : ".",
      "whiteSpace" : false
    } ]
  }, {
    "id" : "s4",
    "begin" : 512,
    "end" : 685,
    "text" : "Redator do jornal Correio da Manhã, no Rio de Janeiro, e cronista\rjudiciário de 1906 a 1910, já em 1909 tornou-se também inspetor de\reducação, função que exerceria até 1911.",
    "tokens" : [ {
      "id" : "s4-t0",
      "begin" : 512,
      "end" : 519,
      "text" : "Redator",
      "whiteSpace" : false
    }, {
      "id" : "s4-t1",
      "begin" : 520,
      "end" : 522,
      "text" : "do",
      "whiteSpace" : false
    }, {
      "id" : "s4-t2",
      "begin" : 523,
      "end" : 529,
      "text" : "jornal",
      "whiteSpace" : false
    }, {
      "id" : "s4-t3",
      "begin" : 530,
      "end" : 537,
      "text" : "Correio",
      "whiteSpace" : false
    }, {
      "id" : "s4-t4",
      "begin" : 538,
      "end" : 540,
      "text" : "da",
      "whiteSpace" : false
    }, {
      "id" : "s4-t5",
      "begin" : 541,
      "end" : 546,
      "text" : "Manhã",
      "whiteSpace" : false
    }, {
      "id" : "s4-t6",
      "begin" : 546,
      "end" : 547,
      "text" : ",",
      "whiteSpace" : false
    }, {
      "id" : "s4-t7",
      "begin" : 548,
      "end" : 550,
      "text" : "no",
      "whiteSpace" : false
    }, {
      "id" : "s4-t8",
      "begin" : 551,
      "end" : 554,
      "text" : "Rio",
      "whiteSpace" : false
    }, {
      "id" : "s4-t9",
      "begin" : 555,
      "end" : 557,
      "text" : "de",
      "whiteSpace" : false
    }, {
      "id" : "s4-t10",
      "begin" : 558,
      "end" : 565,
      "text" : "Janeiro",
      "whiteSpace" : false
    }, {
      "id" : "s4-t11",
      "begin" : 565,
      "end" : 566,
      "text" : ",",
      "whiteSpace" : false
    }, {
      "id" : "s4-t12",
      "begin" : 567,
      "end" : 568,
      "text" : "e",
      "whiteSpace" : false
    }, {
      "id" : "s4-t13",
      "begin" : 569,
      "end" : 577,
      "text" : "cronista",
      "whiteSpace" : false
    }, {
      "id" : "s4-t14",
      "begin" : 578,
      "end" : 588,
      "text" : "judiciário",
      "whiteSpace" : false
    }, {
      "id" : "s4-t15",
      "begin" : 589,
      "end" : 591,
      "text" : "de",
      "whiteSpace" : false
    }, {
      "id" : "s4-t16",
      "begin" : 592,
      "end" : 596,
      "text" : "1906",
      "whiteSpace" : false
    }, {
      "id" : "s4-t17",
      "begin" : 597,
      "end" : 598,
      "text" : "a",
      "whiteSpace" : false
    }, {
      "id" : "s4-t18",
      "begin" : 599,
      "end" : 603,
      "text" : "1910",
      "whiteSpace" : false
    }, {
      "id" : "s4-t19",
      "begin" : 603,
      "end" : 604,
      "text" : ",",
      "whiteSpace" : false
    }, {
      "id" : "s4-t20",
      "begin" : 605,
      "end" : 607,
      "text" : "já",
      "whiteSpace" : false
    }, {
      "id" : "s4-t21",
      "begin" : 608,
      "end" : 610,
      "text" : "em",
      "whiteSpace" : false
    }, {
      "id" : "s4-t22",
      "begin" : 611,
      "end" : 615,
      "text" : "1909",
      "whiteSpace" : false
    }, {
      "id" : "s4-t23",
      "begin" : 616,
      "end" : 625,
      "text" : "tornou-se",
      "whiteSpace" : false
    }, {
      "id" : "s4-t24",
      "begin" : 626,
      "end" : 632,
      "text" : "também",
      "whiteSpace" : false
    }, {
      "id" : "s4-t25",
      "begin" : 633,
      "end" : 641,
      "text" : "inspetor",
      "whiteSpace" : false
    }, {
      "id" : "s4-t26",
      "begin" : 642,
      "end" : 644,
      "text" : "de",
      "whiteSpace" : false
    }, {
      "id" : "s4-t27",
      "begin" : 645,
      "end" : 653,
      "text" : "educação",
      "whiteSpace" : false
    }, {
      "id" : "s4-t28",
      "begin" : 653,
      "end" : 654,
      "text" : ",",
      "whiteSpace" : false
    }, {
      "id" : "s4-t29",
      "begin" : 655,
      "end" : 661,
      "text" : "função",
      "whiteSpace" : false
    }, {
      "id" : "s4-t30",
      "begin" : 662,
      "end" : 665,
      "text" : "que",
      "whiteSpace" : false
    }, {
      "id" : "s4-t31",
      "begin" : 666,
      "end" : 675,
      "text" : "exerceria",
      "whiteSpace" : false
    }, {
      "id" : "s4-t32",
      "begin" : 676,
      "end" : 679,
      "text" : "até",
      "whiteSpace" : false
    }, {
      "id" : "s4-t33",
      "begin" : 680,
      "end" : 684,
      "text" : "1911",
      "whiteSpace" : false
    }, {
      "id" : "s4-t34",
      "begin" : 684,
      "end" : 685,
      "text" : ".",
      "whiteSpace" : false
    } ]
  }, {
    "id" : "s5",
    "begin" : 686,
    "end" : 860,
    "text" : "No ano seguinte passou a\rredator do jornal carioca *A Noite*, do qual se desligou em 1915 para\ratuar como advogado municipal em Niterói na qualidade de procurador dos\rFeitos.",
    "tokens" : [ {
      "id" : "s5-t0",
      "begin" : 686,
      "end" : 688,
      "text" : "No",
      "whiteSpace" : false
    }, {
      "id" : "s5-t1",
      "begin" : 689,
      "end" : 692,
      "text" : "ano",
      "whiteSpace" : false
    }, {
      "id" : "s5-t2",
      "begin" : 693,
      "end" : 701,
      "text" : "seguinte",
      "whiteSpace" : false
    }, {
      "id" : "s5-t3",
      "begin" : 702,
      "end" : 708,
      "text" : "passou",
      "whiteSpace" : false
    }, {
      "id" : "s5-t4",
      "begin" : 709,
      "end" : 710,
      "text" : "a",
      "whiteSpace" : false
    }, {
      "id" : "s5-t5",
      "begin" : 711,
      "end" : 718,
      "text" : "redator",
      "whiteSpace" : false
    }, {
      "id" : "s5-t6",
      "begin" : 719,
      "end" : 721,
      "text" : "do",
      "whiteSpace" : false
    }, {
      "id" : "s5-t7",
      "begin" : 722,
      "end" : 728,
      "text" : "jornal",
      "whiteSpace" : false
    }, {
      "id" : "s5-t8",
      "begin" : 729,
      "end" : 736,
      "text" : "carioca",
      "whiteSpace" : false
    }, {
      "id" : "s5-t9",
      "begin" : 737,
      "end" : 739,
      "text" : "*A",
      "whiteSpace" : false
    }, {
      "id" : "s5-t10",
      "begin" : 740,
      "end" : 745,
      "text" : "Noite",
      "whiteSpace" : false
    }, {
      "id" : "s5-t11",
      "begin" : 745,
      "end" : 746,
      "text" : "*",
      "whiteSpace" : false
    }, {
      "id" : "s5-t12",
      "begin" : 746,
      "end" : 747,
      "text" : ",",
      "whiteSpace" : false
    }, {
      "id" : "s5-t13",
      "begin" : 748,
      "end" : 750,
      "text" : "do",
      "whiteSpace" : false
    }, {
      "id" : "s5-t14",
      "begin" : 751,
      "end" : 755,
      "text" : "qual",
      "whiteSpace" : false
    }, {
      "id" : "s5-t15",
      "begin" : 756,
      "end" : 758,
      "text" : "se",
      "whiteSpace" : false
    }, {
      "id" : "s5-t16",
      "begin" : 759,
      "end" : 767,
      "text" : "desligou",
      "whiteSpace" : false
    }, {
      "id" : "s5-t17",
      "begin" : 768,
      "end" : 770,
      "text" : "em",
      "whiteSpace" : false
    }, {
      "id" : "s5-t18",
      "begin" : 771,
      "end" : 775,
      "text" : "1915",
      "whiteSpace" : false
    }, {
      "id" : "s5-t19",
      "begin" : 776,
      "end" : 780,
      "text" : "para",
      "whiteSpace" : false
    }, {
      "id" : "s5-t20",
      "begin" : 781,
      "end" : 786,
      "text" : "atuar",
      "whiteSpace" : false
    }, {
      "id" : "s5-t21",
      "begin" : 787,
      "end" : 791,
      "text" : "como",
      "whiteSpace" : false
    }, {
      "id" : "s5-t22",
      "begin" : 792,
      "end" : 800,
      "text" : "advogado",
      "whiteSpace" : false
    }, {
      "id" : "s5-t23",
      "begin" : 801,
      "end" : 810,
      "text" : "municipal",
      "whiteSpace" : false
    }, {
      "id" : "s5-t24",
      "begin" : 811,
      "end" : 813,
      "text" : "em",
      "whiteSpace" : false
    }, {
      "id" : "s5-t25",
      "begin" : 814,
      "end" : 821,
      "text" : "Niterói",
      "whiteSpace" : false
    }, {
      "id" : "s5-t26",
      "begin" : 822,
      "end" : 824,
      "text" : "na",
      "whiteSpace" : false
    }, {
      "id" : "s5-t27",
      "begin" : 825,
      "end" : 834,
      "text" : "qualidade",
      "whiteSpace" : false
    }, {
      "id" : "s5-t28",
      "begin" : 835,
      "end" : 837,
      "text" : "de",
      "whiteSpace" : false
    }, {
      "id" : "s5-t29",
      "begin" : 838,
      "end" : 848,
      "text" : "procurador",
      "whiteSpace" : false
    }, {
      "id" : "s5-t30",
      "begin" : 849,
      "end" : 852,
      "text" : "dos",
      "whiteSpace" : false
    }, {
      "id" : "s5-t31",
      "begin" : 853,
      "end" : 859,
      "text" : "Feitos",
      "whiteSpace" : false
    }, {
      "id" : "s5-t32",
      "begin" : 859,
      "end" : 860,
      "text" : ".",
      "whiteSpace" : false
    } ]
  }, {
    "id" : "s6",
    "begin" : 861,
    "end" : 1079,
    "text" : "Exerceu essa função até 1931 e, durante esse período, ocupou\rtambém o cargo de diretor da Caixa Econômica Federal no Rio de Janeiro\rentre maio de 1927 e janeiro de 1928, quando se tornou vice-presidente\rda instituição.",
    "tokens" : [ {
      "id" : "s6-t0",
      "begin" : 861,
      "end" : 868,
      "text" : "Exerceu",
      "whiteSpace" : false
    }, {
      "id" : "s6-t1",
      "begin" : 869,
      "end" : 873,
      "text" : "essa",
      "whiteSpace" : false
    }, {
      "id" : "s6-t2",
      "begin" : 874,
      "end" : 880,
      "text" : "função",
      "whiteSpace" : false
    }, {
      "id" : "s6-t3",
      "begin" : 881,
      "end" : 884,
      "text" : "até",
      "whiteSpace" : false
    }, {
      "id" : "s6-t4",
      "begin" : 885,
      "end" : 889,
      "text" : "1931",
      "whiteSpace" : false
    }, {
      "id" : "s6-t5",
      "begin" : 890,
      "end" : 891,
      "text" : "e",
      "whiteSpace" : false
    }, {
      "id" : "s6-t6",
      "begin" : 891,
      "end" : 892,
      "text" : ",",
      "whiteSpace" : false
    }, {
      "id" : "s6-t7",
      "begin" : 893,
      "end" : 900,
      "text" : "durante",
      "whiteSpace" : false
    }, {
      "id" : "s6-t8",
      "begin" : 901,
      "end" : 905,
      "text" : "esse",
      "whiteSpace" : false
    }, {
      "id" : "s6-t9",
      "begin" : 906,
      "end" : 913,
      "text" : "período",
      "whiteSpace" : false
    }, {
      "id" : "s6-t10",
      "begin" : 913,
      "end" : 914,
      "text" : ",",
      "whiteSpace" : false
    }, {
      "id" : "s6-t11",
      "begin" : 915,
      "end" : 921,
      "text" : "ocupou",
      "whiteSpace" : false
    }, {
      "id" : "s6-t12",
      "begin" : 922,
      "end" : 928,
      "text" : "também",
      "whiteSpace" : false
    }, {
      "id" : "s6-t13",
      "begin" : 929,
      "end" : 930,
      "text" : "o",
      "whiteSpace" : false
    }, {
      "id" : "s6-t14",
      "begin" : 931,
      "end" : 936,
      "text" : "cargo",
      "whiteSpace" : false
    }, {
      "id" : "s6-t15",
      "begin" : 937,
      "end" : 939,
      "text" : "de",
      "whiteSpace" : false
    }, {
      "id" : "s6-t16",
      "begin" : 940,
      "end" : 947,
      "text" : "diretor",
      "whiteSpace" : false
    }, {
      "id" : "s6-t17",
      "begin" : 948,
      "end" : 950,
      "text" : "da",
      "whiteSpace" : false
    }, {
      "id" : "s6-t18",
      "begin" : 951,
      "end" : 956,
      "text" : "Caixa",
      "whiteSpace" : false
    }, {
      "id" : "s6-t19",
      "begin" : 957,
      "end" : 966,
      "text" : "Econômica",
      "whiteSpace" : false
    }, {
      "id" : "s6-t20",
      "begin" : 967,
      "end" : 974,
      "text" : "Federal",
      "whiteSpace" : false
    }, {
      "id" : "s6-t21",
      "begin" : 975,
      "end" : 977,
      "text" : "no",
      "whiteSpace" : false
    }, {
      "id" : "s6-t22",
      "begin" : 978,
      "end" : 981,
      "text" : "Rio",
      "whiteSpace" : false
    }, {
      "id" : "s6-t23",
      "begin" : 982,
      "end" : 984,
      "text" : "de",
      "whiteSpace" : false
    }, {
      "id" : "s6-t24",
      "begin" : 985,
      "end" : 992,
      "text" : "Janeiro",
      "whiteSpace" : false
    }, {
      "id" : "s6-t25",
      "begin" : 993,
      "end" : 998,
      "text" : "entre",
      "whiteSpace" : false
    }, {
      "id" : "s6-t26",
      "begin" : 999,
      "end" : 1003,
      "text" : "maio",
      "whiteSpace" : false
    }, {
      "id" : "s6-t27",
      "begin" : 1004,
      "end" : 1006,
      "text" : "de",
      "whiteSpace" : false
    }, {
      "id" : "s6-t28",
      "begin" : 1007,
      "end" : 1011,
      "text" : "1927",
      "whiteSpace" : false
    }, {
      "id" : "s6-t29",
      "begin" : 1012,
      "end" : 1013,
      "text" : "e",
      "whiteSpace" : false
    }, {
      "id" : "s6-t30",
      "begin" : 1014,
      "end" : 1021,
      "text" : "janeiro",
      "whiteSpace" : false
    }, {
      "id" : "s6-t31",
      "begin" : 1022,
      "end" : 1024,
      "text" : "de",
      "whiteSpace" : false
    }, {
      "id" : "s6-t32",
      "begin" : 1025,
      "end" : 1029,
      "text" : "1928",
      "whiteSpace" : false
    }, {
      "id" : "s6-t33",
      "begin" : 1029,
      "end" : 1030,
      "text" : ",",
      "whiteSpace" : false
    }, {
      "id" : "s6-t34",
      "begin" : 1031,
      "end" : 1037,
      "text" : "quando",
      "whiteSpace" : false
    }, {
      "id" : "s6-t35",
      "begin" : 1038,
      "end" : 1040,
      "text" : "se",
      "whiteSpace" : false
    }, {
      "id" : "s6-t36",
      "begin" : 1041,
      "end" : 1047,
      "text" : "tornou",
      "whiteSpace" : false
    }, {
      "id" : "s6-t37",
      "begin" : 1048,
      "end" : 1063,
      "text" : "vice-presidente",
      "whiteSpace" : false
    }, {
      "id" : "s6-t38",
      "begin" : 1064,
      "end" : 1066,
      "text" : "da",
      "whiteSpace" : false
    }, {
      "id" : "s6-t39",
      "begin" : 1067,
      "end" : 1078,
      "text" : "instituição",
      "whiteSpace" : false
    }, {
      "id" : "s6-t40",
      "begin" : 1078,
      "end" : 1079,
      "text" : ".",
      "whiteSpace" : false
    } ]
  }, {
    "id" : "s7",
    "begin" : 1081,
    "end" : 1194,
    "text" : "Após a Revolução de 1930, atuou como juiz federal substituto na seção do\restado do Rio de Janeiro de 1931 a 1934.",
    "tokens" : [ {
      "id" : "s7-t0",
      "begin" : 1081,
      "end" : 1085,
      "text" : "Após",
      "whiteSpace" : false
    }, {
      "id" : "s7-t1",
      "begin" : 1086,
      "end" : 1087,
      "text" : "a",
      "whiteSpace" : false
    }, {
      "id" : "s7-t2",
      "begin" : 1088,
      "end" : 1097,
      "text" : "Revolução",
      "whiteSpace" : false
    }, {
      "id" : "s7-t3",
      "begin" : 1098,
      "end" : 1100,
      "text" : "de",
      "whiteSpace" : false
    }, {
      "id" : "s7-t4",
      "begin" : 1101,
      "end" : 1105,
      "text" : "1930",
      "whiteSpace" : false
    }, {
      "id" : "s7-t5",
      "begin" : 1105,
      "end" : 1106,
      "text" : ",",
      "whiteSpace" : false
    }, {
      "id" : "s7-t6",
      "begin" : 1107,
      "end" : 1112,
      "text" : "atuou",
      "whiteSpace" : false
    }, {
      "id" : "s7-t7",
      "begin" : 1113,
      "end" : 1117,
      "text" : "como",
      "whiteSpace" : false
    }, {
      "id" : "s7-t8",
      "begin" : 1118,
      "end" : 1122,
      "text" : "juiz",
      "whiteSpace" : false
    }, {
      "id" : "s7-t9",
      "begin" : 1123,
      "end" : 1130,
      "text" : "federal",
      "whiteSpace" : false
    }, {
      "id" : "s7-t10",
      "begin" : 1131,
      "end" : 1141,
      "text" : "substituto",
      "whiteSpace" : false
    }, {
      "id" : "s7-t11",
      "begin" : 1142,
      "end" : 1144,
      "text" : "na",
      "whiteSpace" : false
    }, {
      "id" : "s7-t12",
      "begin" : 1145,
      "end" : 1150,
      "text" : "seção",
      "whiteSpace" : false
    }, {
      "id" : "s7-t13",
      "begin" : 1151,
      "end" : 1153,
      "text" : "do",
      "whiteSpace" : false
    }, {
      "id" : "s7-t14",
      "begin" : 1154,
      "end" : 1160,
      "text" : "estado",
      "whiteSpace" : false
    }, {
      "id" : "s7-t15",
      "begin" : 1161,
      "end" : 1163,
      "text" : "do",
      "whiteSpace" : false
    }, {
      "id" : "s7-t16",
      "begin" : 1164,
      "end" : 1167,
      "text" : "Rio",
      "whiteSpace" : false
    }, {
      "id" : "s7-t17",
      "begin" : 1168,
      "end" : 1170,
      "text" : "de",
      "whiteSpace" : false
    }, {
      "id" : "s7-t18",
      "begin" : 1171,
      "end" : 1178,
      "text" : "Janeiro",
      "whiteSpace" : false
    }, {
      "id" : "s7-t19",
      "begin" : 1179,
      "end" : 1181,
      "text" : "de",
      "whiteSpace" : false
    }, {
      "id" : "s7-t20",
      "begin" : 1182,
      "end" : 1186,
      "text" : "1931",
      "whiteSpace" : false
    }, {
      "id" : "s7-t21",
      "begin" : 1187,
      "end" : 1188,
      "text" : "a",
      "whiteSpace" : false
    }, {
      "id" : "s7-t22",
      "begin" : 1189,
      "end" : 1193,
      "text" : "1934",
      "whiteSpace" : false
    }, {
      "id" : "s7-t23",
      "begin" : 1193,
      "end" : 1194,
      "text" : ".",
      "whiteSpace" : false
    } ]
  }, {
    "id" : "s8",
    "begin" : 1195,
    "end" : 1364,
    "text" : "Nesse mesmo tempo integrou, em\r1932, a comissão encarregada de elaborar o anteprojeto de Constituição\rapresentado à Assembléia Nacional Constituinte em novembro de 1933.",
    "tokens" : [ {
      "id" : "s8-t0",
      "begin" : 1195,
      "end" : 1200,
      "text" : "Nesse",
      "whiteSpace" : false
    }, {
      "id" : "s8-t1",
      "begin" : 1201,
      "end" : 1206,
      "text" : "mesmo",
      "whiteSpace" : false
    }, {
      "id" : "s8-t2",
      "begin" : 1207,
      "end" : 1212,
      "text" : "tempo",
      "whiteSpace" : false
    }, {
      "id" : "s8-t3",
      "begin" : 1213,
      "end" : 1221,
      "text" : "integrou",
      "whiteSpace" : false
    }, {
      "id" : "s8-t4",
      "begin" : 1221,
      "end" : 1222,
      "text" : ",",
      "whiteSpace" : false
    }, {
      "id" : "s8-t5",
      "begin" : 1223,
      "end" : 1225,
      "text" : "em",
      "whiteSpace" : false
    }, {
      "id" : "s8-t6",
      "begin" : 1226,
      "end" : 1230,
      "text" : "1932",
      "whiteSpace" : false
    }, {
      "id" : "s8-t7",
      "begin" : 1230,
      "end" : 1231,
      "text" : ",",
      "whiteSpace" : false
    }, {
      "id" : "s8-t8",
      "begin" : 1232,
      "end" : 1233,
      "text" : "a",
      "whiteSpace" : false
    }, {
      "id" : "s8-t9",
      "begin" : 1234,
      "end" : 1242,
      "text" : "comissão",
      "whiteSpace" : false
    }, {
      "id" : "s8-t10",
      "begin" : 1243,
      "end" : 1254,
      "text" : "encarregada",
      "whiteSpace" : false
    }, {
      "id" : "s8-t11",
      "begin" : 1255,
      "end" : 1257,
      "text" : "de",
      "whiteSpace" : false
    }, {
      "id" : "s8-t12",
      "begin" : 1258,
      "end" : 1266,
      "text" : "elaborar",
      "whiteSpace" : false
    }, {
      "id" : "s8-t13",
      "begin" : 1267,
      "end" : 1268,
      "text" : "o",
      "whiteSpace" : false
    }, {
      "id" : "s8-t14",
      "begin" : 1269,
      "end" : 1280,
      "text" : "anteprojeto",
      "whiteSpace" : false
    }, {
      "id" : "s8-t15",
      "begin" : 1281,
      "end" : 1283,
      "text" : "de",
      "whiteSpace" : false
    }, {
      "id" : "s8-t16",
      "begin" : 1284,
      "end" : 1296,
      "text" : "Constituição",
      "whiteSpace" : false
    }, {
      "id" : "s8-t17",
      "begin" : 1297,
      "end" : 1308,
      "text" : "apresentado",
      "whiteSpace" : false
    }, {
      "id" : "s8-t18",
      "begin" : 1309,
      "end" : 1310,
      "text" : "à",
      "whiteSpace" : false
    }, {
      "id" : "s8-t19",
      "begin" : 1311,
      "end" : 1321,
      "text" : "Assembléia",
      "whiteSpace" : false
    }, {
      "id" : "s8-t20",
      "begin" : 1322,
      "end" : 1330,
      "text" : "Nacional",
      "whiteSpace" : false
    }, {
      "id" : "s8-t21",
      "begin" : 1331,
      "end" : 1343,
      "text" : "Constituinte",
      "whiteSpace" : false
    }, {
      "id" : "s8-t22",
      "begin" : 1344,
      "end" : 1346,
      "text" : "em",
      "whiteSpace" : false
    }, {
      "id" : "s8-t23",
      "begin" : 1347,
      "end" : 1355,
      "text" : "novembro",
      "whiteSpace" : false
    }, {
      "id" : "s8-t24",
      "begin" : 1356,
      "end" : 1358,
      "text" : "de",
      "whiteSpace" : false
    }, {
      "id" : "s8-t25",
      "begin" : 1359,
      "end" : 1363,
      "text" : "1933",
      "whiteSpace" : false
    }, {
      "id" : "s8-t26",
      "begin" : 1363,
      "end" : 1364,
      "text" : ".",
      "whiteSpace" : false
    } ]
  }, {
    "id" : "s9",
    "begin" : 1365,
    "end" : 1475,
    "text" : "No\rano seguinte passou a juiz federal na 2ª Vara da seção do Distrito\rFederal, exercendo essa função até 1937.",
    "tokens" : [ {
      "id" : "s9-t0",
      "begin" : 1365,
      "end" : 1367,
      "text" : "No",
      "whiteSpace" : false
    }, {
      "id" : "s9-t1",
      "begin" : 1368,
      "end" : 1371,
      "text" : "ano",
      "whiteSpace" : false
    }, {
      "id" : "s9-t2",
      "begin" : 1372,
      "end" : 1380,
      "text" : "seguinte",
      "whiteSpace" : false
    }, {
      "id" : "s9-t3",
      "begin" : 1381,
      "end" : 1387,
      "text" : "passou",
      "whiteSpace" : false
    }, {
      "id" : "s9-t4",
      "begin" : 1388,
      "end" : 1389,
      "text" : "a",
      "whiteSpace" : false
    }, {
      "id" : "s9-t5",
      "begin" : 1390,
      "end" : 1394,
      "text" : "juiz",
      "whiteSpace" : false
    }, {
      "id" : "s9-t6",
      "begin" : 1395,
      "end" : 1402,
      "text" : "federal",
      "whiteSpace" : false
    }, {
      "id" : "s9-t7",
      "begin" : 1403,
      "end" : 1405,
      "text" : "na",
      "whiteSpace" : false
    }, {
      "id" : "s9-t8",
      "begin" : 1406,
      "end" : 1408,
      "text" : "2ª",
      "whiteSpace" : false
    }, {
      "id" : "s9-t9",
      "begin" : 1409,
      "end" : 1413,
      "text" : "Vara",
      "whiteSpace" : false
    }, {
      "id" : "s9-t10",
      "begin" : 1414,
      "end" : 1416,
      "text" : "da",
      "whiteSpace" : false
    }, {
      "id" : "s9-t11",
      "begin" : 1417,
      "end" : 1422,
      "text" : "seção",
      "whiteSpace" : false
    }, {
      "id" : "s9-t12",
      "begin" : 1423,
      "end" : 1425,
      "text" : "do",
      "whiteSpace" : false
    }, {
      "id" : "s9-t13",
      "begin" : 1426,
      "end" : 1434,
      "text" : "Distrito",
      "whiteSpace" : false
    }, {
      "id" : "s9-t14",
      "begin" : 1435,
      "end" : 1442,
      "text" : "Federal",
      "whiteSpace" : false
    }, {
      "id" : "s9-t15",
      "begin" : 1442,
      "end" : 1443,
      "text" : ",",
      "whiteSpace" : false
    }, {
      "id" : "s9-t16",
      "begin" : 1444,
      "end" : 1453,
      "text" : "exercendo",
      "whiteSpace" : false
    }, {
      "id" : "s9-t17",
      "begin" : 1454,
      "end" : 1458,
      "text" : "essa",
      "whiteSpace" : false
    }, {
      "id" : "s9-t18",
      "begin" : 1459,
      "end" : 1465,
      "text" : "função",
      "whiteSpace" : false
    }, {
      "id" : "s9-t19",
      "begin" : 1466,
      "end" : 1469,
      "text" : "até",
      "whiteSpace" : false
    }, {
      "id" : "s9-t20",
      "begin" : 1470,
      "end" : 1474,
      "text" : "1937",
      "whiteSpace" : false
    }, {
      "id" : "s9-t21",
      "begin" : 1474,
      "end" : 1475,
      "text" : ".",
      "whiteSpace" : false
    } ]
  }, {
    "id" : "s10",
    "begin" : 1476,
    "end" : 1585,
    "text" : "Tornou-se então juiz da 2ª Vara\rdos Feitos da Fazenda Pública no Distrito Federal, cargo que ocupou até\r1938.",
    "tokens" : [ {
      "id" : "s10-t0",
      "begin" : 1476,
      "end" : 1485,
      "text" : "Tornou-se",
      "whiteSpace" : false
    }, {
      "id" : "s10-t1",
      "begin" : 1486,
      "end" : 1491,
      "text" : "então",
      "whiteSpace" : false
    }, {
      "id" : "s10-t2",
      "begin" : 1492,
      "end" : 1496,
      "text" : "juiz",
      "whiteSpace" : false
    }, {
      "id" : "s10-t3",
      "begin" : 1497,
      "end" : 1499,
      "text" : "da",
      "whiteSpace" : false
    }, {
      "id" : "s10-t4",
      "begin" : 1500,
      "end" : 1502,
      "text" : "2ª",
      "whiteSpace" : false
    }, {
      "id" : "s10-t5",
      "begin" : 1503,
      "end" : 1507,
      "text" : "Vara",
      "whiteSpace" : false
    }, {
      "id" : "s10-t6",
      "begin" : 1508,
      "end" : 1511,
      "text" : "dos",
      "whiteSpace" : false
    }, {
      "id" : "s10-t7",
      "begin" : 1512,
      "end" : 1518,
      "text" : "Feitos",
      "whiteSpace" : false
    }, {
      "id" : "s10-t8",
      "begin" : 1519,
      "end" : 1521,
      "text" : "da",
      "whiteSpace" : false
    }, {
      "id" : "s10-t9",
      "begin" : 1522,
      "end" : 1529,
      "text" : "Fazenda",
      "whiteSpace" : false
    }, {
      "id" : "s10-t10",
      "begin" : 1530,
      "end" : 1537,
      "text" : "Pública",
      "whiteSpace" : false
    }, {
      "id" : "s10-t11",
      "begin" : 1538,
      "end" : 1540,
      "text" : "no",
      "whiteSpace" : false
    }, {
      "id" : "s10-t12",
      "begin" : 1541,
      "end" : 1549,
      "text" : "Distrito",
      "whiteSpace" : false
    }, {
      "id" : "s10-t13",
      "begin" : 1550,
      "end" : 1557,
      "text" : "Federal",
      "whiteSpace" : false
    }, {
      "id" : "s10-t14",
      "begin" : 1557,
      "end" : 1558,
      "text" : ",",
      "whiteSpace" : false
    }, {
      "id" : "s10-t15",
      "begin" : 1559,
      "end" : 1564,
      "text" : "cargo",
      "whiteSpace" : false
    }, {
      "id" : "s10-t16",
      "begin" : 1565,
      "end" : 1568,
      "text" : "que",
      "whiteSpace" : false
    }, {
      "id" : "s10-t17",
      "begin" : 1569,
      "end" : 1575,
      "text" : "ocupou",
      "whiteSpace" : false
    }, {
      "id" : "s10-t18",
      "begin" : 1576,
      "end" : 1579,
      "text" : "até",
      "whiteSpace" : false
    }, {
      "id" : "s10-t19",
      "begin" : 1580,
      "end" : 1584,
      "text" : "1938",
      "whiteSpace" : false
    }, {
      "id" : "s10-t20",
      "begin" : 1584,
      "end" : 1585,
      "text" : ".",
      "whiteSpace" : false
    } ]
  }, {
    "id" : "s11",
    "begin" : 1587,
    "end" : 1778,
    "text" : "Durante o Estado Novo (1937-1945), atuou como membro do Tribunal de\rContas da União (TCU) no período de 1938 a 1940, sendo nomeado neste\rúltimo ano ministro do Supremo Tribunal Federal (STF).",
    "tokens" : [ {
      "id" : "s11-t0",
      "begin" : 1587,
      "end" : 1594,
      "text" : "Durante",
      "whiteSpace" : false
    }, {
      "id" : "s11-t1",
      "begin" : 1595,
      "end" : 1596,
      "text" : "o",
      "whiteSpace" : false
    }, {
      "id" : "s11-t2",
      "begin" : 1597,
      "end" : 1603,
      "text" : "Estado",
      "whiteSpace" : false
    }, {
      "id" : "s11-t3",
      "begin" : 1604,
      "end" : 1608,
      "text" : "Novo",
      "whiteSpace" : false
    }, {
      "id" : "s11-t4",
      "begin" : 1609,
      "end" : 1610,
      "text" : "(",
      "whiteSpace" : false
    }, {
      "id" : "s11-t5",
      "begin" : 1610,
      "end" : 1619,
      "text" : "1937-1945",
      "whiteSpace" : false
    }, {
      "id" : "s11-t6",
      "begin" : 1619,
      "end" : 1620,
      "text" : ")",
      "whiteSpace" : false
    }, {
      "id" : "s11-t7",
      "begin" : 1620,
      "end" : 1621,
      "text" : ",",
      "whiteSpace" : false
    }, {
      "id" : "s11-t8",
      "begin" : 1622,
      "end" : 1627,
      "text" : "atuou",
      "whiteSpace" : false
    }, {
      "id" : "s11-t9",
      "begin" : 1628,
      "end" : 1632,
      "text" : "como",
      "whiteSpace" : false
    }, {
      "id" : "s11-t10",
      "begin" : 1633,
      "end" : 1639,
      "text" : "membro",
      "whiteSpace" : false
    }, {
      "id" : "s11-t11",
      "begin" : 1640,
      "end" : 1642,
      "text" : "do",
      "whiteSpace" : false
    }, {
      "id" : "s11-t12",
      "begin" : 1643,
      "end" : 1651,
      "text" : "Tribunal",
      "whiteSpace" : false
    }, {
      "id" : "s11-t13",
      "begin" : 1652,
      "end" : 1654,
      "text" : "de",
      "whiteSpace" : false
    }, {
      "id" : "s11-t14",
      "begin" : 1655,
      "end" : 1661,
      "text" : "Contas",
      "whiteSpace" : false
    }, {
      "id" : "s11-t15",
      "begin" : 1662,
      "end" : 1664,
      "text" : "da",
      "whiteSpace" : false
    }, {
      "id" : "s11-t16",
      "begin" : 1665,
      "end" : 1670,
      "text" : "União",
      "whiteSpace" : false
    }, {
      "id" : "s11-t17",
      "begin" : 1671,
      "end" : 1672,
      "text" : "(",
      "whiteSpace" : false
    }, {
      "id" : "s11-t18",
      "begin" : 1672,
      "end" : 1675,
      "text" : "TCU",
      "whiteSpace" : false
    }, {
      "id" : "s11-t19",
      "begin" : 1675,
      "end" : 1676,
      "text" : ")",
      "whiteSpace" : false
    }, {
      "id" : "s11-t20",
      "begin" : 1677,
      "end" : 1679,
      "text" : "no",
      "whiteSpace" : false
    }, {
      "id" : "s11-t21",
      "begin" : 1680,
      "end" : 1687,
      "text" : "período",
      "whiteSpace" : false
    }, {
      "id" : "s11-t22",
      "begin" : 1688,
      "end" : 1690,
      "text" : "de",
      "whiteSpace" : false
    }, {
      "id" : "s11-t23",
      "begin" : 1691,
      "end" : 1695,
      "text" : "1938",
      "whiteSpace" : false
    }, {
      "id" : "s11-t24",
      "begin" : 1696,
      "end" : 1697,
      "text" : "a",
      "whiteSpace" : false
    }, {
      "id" : "s11-t25",
      "begin" : 1698,
      "end" : 1702,
      "text" : "1940",
      "whiteSpace" : false
    }, {
      "id" : "s11-t26",
      "begin" : 1702,
      "end" : 1703,
      "text" : ",",
      "whiteSpace" : false
    }, {
      "id" : "s11-t27",
      "begin" : 1704,
      "end" : 1709,
      "text" : "sendo",
      "whiteSpace" : false
    }, {
      "id" : "s11-t28",
      "begin" : 1710,
      "end" : 1717,
      "text" : "nomeado",
      "whiteSpace" : false
    }, {
      "id" : "s11-t29",
      "begin" : 1718,
      "end" : 1723,
      "text" : "neste",
      "whiteSpace" : false
    }, {
      "id" : "s11-t30",
      "begin" : 1724,
      "end" : 1730,
      "text" : "último",
      "whiteSpace" : false
    }, {
      "id" : "s11-t31",
      "begin" : 1731,
      "end" : 1734,
      "text" : "ano",
      "whiteSpace" : false
    }, {
      "id" : "s11-t32",
      "begin" : 1735,
      "end" : 1743,
      "text" : "ministro",
      "whiteSpace" : false
    }, {
      "id" : "s11-t33",
      "begin" : 1744,
      "end" : 1746,
      "text" : "do",
      "whiteSpace" : false
    }, {
      "id" : "s11-t34",
      "begin" : 1747,
      "end" : 1754,
      "text" : "Supremo",
      "whiteSpace" : false
    }, {
      "id" : "s11-t35",
      "begin" : 1755,
      "end" : 1763,
      "text" : "Tribunal",
      "whiteSpace" : false
    }, {
      "id" : "s11-t36",
      "begin" : 1764,
      "end" : 1771,
      "text" : "Federal",
      "whiteSpace" : false
    }, {
      "id" : "s11-t37",
      "begin" : 1772,
      "end" : 1773,
      "text" : "(",
      "whiteSpace" : false
    }, {
      "id" : "s11-t38",
      "begin" : 1773,
      "end" : 1776,
      "text" : "STF",
      "whiteSpace" : false
    }, {
      "id" : "s11-t39",
      "begin" : 1776,
      "end" : 1777,
      "text" : ")",
      "whiteSpace" : false
    }, {
      "id" : "s11-t40",
      "begin" : 1777,
      "end" : 1778,
      "text" : ".",
      "whiteSpace" : false
    } ]
  }, {
    "id" : "s12",
    "begin" : 1779,
    "end" : 2104,
    "text" : "Presidente\rinterino (1945-1946) e vice-presidente (1945-1949) dessa corte, em maio\rde 1947 votou contra o *habeas-corpus* requerido por dirigentes comunistas\rsob a alegação de que estavam impedidos de entrar e sair da sede central\re dos comitês locais do Partido Comunista Brasileiro, então Partido\rComunista do Brasil (PCB).",
    "tokens" : [ {
      "id" : "s12-t0",
      "begin" : 1779,
      "end" : 1789,
      "text" : "Presidente",
      "whiteSpace" : false
    }, {
      "id" : "s12-t1",
      "begin" : 1790,
      "end" : 1798,
      "text" : "interino",
      "whiteSpace" : false
    }, {
      "id" : "s12-t2",
      "begin" : 1799,
      "end" : 1800,
      "text" : "(",
      "whiteSpace" : false
    }, {
      "id" : "s12-t3",
      "begin" : 1800,
      "end" : 1809,
      "text" : "1945-1946",
      "whiteSpace" : false
    }, {
      "id" : "s12-t4",
      "begin" : 1809,
      "end" : 1810,
      "text" : ")",
      "whiteSpace" : false
    }, {
      "id" : "s12-t5",
      "begin" : 1811,
      "end" : 1812,
      "text" : "e",
      "whiteSpace" : false
    }, {
      "id" : "s12-t6",
      "begin" : 1813,
      "end" : 1828,
      "text" : "vice-presidente",
      "whiteSpace" : false
    }, {
      "id" : "s12-t7",
      "begin" : 1829,
      "end" : 1830,
      "text" : "(",
      "whiteSpace" : false
    }, {
      "id" : "s12-t8",
      "begin" : 1830,
      "end" : 1839,
      "text" : "1945-1949",
      "whiteSpace" : false
    }, {
      "id" : "s12-t9",
      "begin" : 1839,
      "end" : 1840,
      "text" : ")",
      "whiteSpace" : false
    }, {
      "id" : "s12-t10",
      "begin" : 1841,
      "end" : 1846,
      "text" : "dessa",
      "whiteSpace" : false
    }, {
      "id" : "s12-t11",
      "begin" : 1847,
      "end" : 1852,
      "text" : "corte",
      "whiteSpace" : false
    }, {
      "id" : "s12-t12",
      "begin" : 1852,
      "end" : 1853,
      "text" : ",",
      "whiteSpace" : false
    }, {
      "id" : "s12-t13",
      "begin" : 1854,
      "end" : 1856,
      "text" : "em",
      "whiteSpace" : false
    }, {
      "id" : "s12-t14",
      "begin" : 1857,
      "end" : 1861,
      "text" : "maio",
      "whiteSpace" : false
    }, {
      "id" : "s12-t15",
      "begin" : 1862,
      "end" : 1864,
      "text" : "de",
      "whiteSpace" : false
    }, {
      "id" : "s12-t16",
      "begin" : 1865,
      "end" : 1869,
      "text" : "1947",
      "whiteSpace" : false
    }, {
      "id" : "s12-t17",
      "begin" : 1870,
      "end" : 1875,
      "text" : "votou",
      "whiteSpace" : false
    }, {
      "id" : "s12-t18",
      "begin" : 1876,
      "end" : 1882,
      "text" : "contra",
      "whiteSpace" : false
    }, {
      "id" : "s12-t19",
      "begin" : 1883,
      "end" : 1884,
      "text" : "o",
      "whiteSpace" : false
    }, {
      "id" : "s12-t20",
      "begin" : 1885,
      "end" : 1886,
      "text" : "*",
      "whiteSpace" : false
    }, {
      "id" : "s12-t21",
      "begin" : 1886,
      "end" : 1899,
      "text" : "habeas-corpus",
      "whiteSpace" : false
    }, {
      "id" : "s12-t22",
      "begin" : 1899,
      "end" : 1900,
      "text" : "*",
      "whiteSpace" : false
    }, {
      "id" : "s12-t23",
      "begin" : 1901,
      "end" : 1910,
      "text" : "requerido",
      "whiteSpace" : false
    }, {
      "id" : "s12-t24",
      "begin" : 1911,
      "end" : 1914,
      "text" : "por",
      "whiteSpace" : false
    }, {
      "id" : "s12-t25",
      "begin" : 1915,
      "end" : 1925,
      "text" : "dirigentes",
      "whiteSpace" : false
    }, {
      "id" : "s12-t26",
      "begin" : 1926,
      "end" : 1936,
      "text" : "comunistas",
      "whiteSpace" : false
    }, {
      "id" : "s12-t27",
      "begin" : 1937,
      "end" : 1940,
      "text" : "sob",
      "whiteSpace" : false
    }, {
      "id" : "s12-t28",
      "begin" : 1941,
      "end" : 1942,
      "text" : "a",
      "whiteSpace" : false
    }, {
      "id" : "s12-t29",
      "begin" : 1943,
      "end" : 1951,
      "text" : "alegação",
      "whiteSpace" : false
    }, {
      "id" : "s12-t30",
      "begin" : 1952,
      "end" : 1954,
      "text" : "de",
      "whiteSpace" : false
    }, {
      "id" : "s12-t31",
      "begin" : 1955,
      "end" : 1958,
      "text" : "que",
      "whiteSpace" : false
    }, {
      "id" : "s12-t32",
      "begin" : 1959,
      "end" : 1966,
      "text" : "estavam",
      "whiteSpace" : false
    }, {
      "id" : "s12-t33",
      "begin" : 1967,
      "end" : 1976,
      "text" : "impedidos",
      "whiteSpace" : false
    }, {
      "id" : "s12-t34",
      "begin" : 1977,
      "end" : 1979,
      "text" : "de",
      "whiteSpace" : false
    }, {
      "id" : "s12-t35",
      "begin" : 1980,
      "end" : 1986,
      "text" : "entrar",
      "whiteSpace" : false
    }, {
      "id" : "s12-t36",
      "begin" : 1987,
      "end" : 1988,
      "text" : "e",
      "whiteSpace" : false
    }, {
      "id" : "s12-t37",
      "begin" : 1989,
      "end" : 1993,
      "text" : "sair",
      "whiteSpace" : false
    }, {
      "id" : "s12-t38",
      "begin" : 1994,
      "end" : 1996,
      "text" : "da",
      "whiteSpace" : false
    }, {
      "id" : "s12-t39",
      "begin" : 1997,
      "end" : 2001,
      "text" : "sede",
      "whiteSpace" : false
    }, {
      "id" : "s12-t40",
      "begin" : 2002,
      "end" : 2009,
      "text" : "central",
      "whiteSpace" : false
    }, {
      "id" : "s12-t41",
      "begin" : 2010,
      "end" : 2011,
      "text" : "e",
      "whiteSpace" : false
    }, {
      "id" : "s12-t42",
      "begin" : 2012,
      "end" : 2015,
      "text" : "dos",
      "whiteSpace" : false
    }, {
      "id" : "s12-t43",
      "begin" : 2016,
      "end" : 2023,
      "text" : "comitês",
      "whiteSpace" : false
    }, {
      "id" : "s12-t44",
      "begin" : 2024,
      "end" : 2030,
      "text" : "locais",
      "whiteSpace" : false
    }, {
      "id" : "s12-t45",
      "begin" : 2031,
      "end" : 2033,
      "text" : "do",
      "whiteSpace" : false
    }, {
      "id" : "s12-t46",
      "begin" : 2034,
      "end" : 2041,
      "text" : "Partido",
      "whiteSpace" : false
    }, {
      "id" : "s12-t47",
      "begin" : 2042,
      "end" : 2051,
      "text" : "Comunista",
      "whiteSpace" : false
    }, {
      "id" : "s12-t48",
      "begin" : 2052,
      "end" : 2062,
      "text" : "Brasileiro",
      "whiteSpace" : false
    }, {
      "id" : "s12-t49",
      "begin" : 2062,
      "end" : 2063,
      "text" : ",",
      "whiteSpace" : false
    }, {
      "id" : "s12-t50",
      "begin" : 2064,
      "end" : 2069,
      "text" : "então",
      "whiteSpace" : false
    }, {
      "id" : "s12-t51",
      "begin" : 2070,
      "end" : 2077,
      "text" : "Partido",
      "whiteSpace" : false
    }, {
      "id" : "s12-t52",
      "begin" : 2078,
      "end" : 2087,
      "text" : "Comunista",
      "whiteSpace" : false
    }, {
      "id" : "s12-t53",
      "begin" : 2088,
      "end" : 2090,
      "text" : "do",
      "whiteSpace" : false
    }, {
      "id" : "s12-t54",
      "begin" : 2091,
      "end" : 2097,
      "text" : "Brasil",
      "whiteSpace" : false
    }, {
      "id" : "s12-t55",
      "begin" : 2098,
      "end" : 2099,
      "text" : "(",
      "whiteSpace" : false
    }, {
      "id" : "s12-t56",
      "begin" : 2099,
      "end" : 2102,
      "text" : "PCB",
      "whiteSpace" : false
    }, {
      "id" : "s12-t57",
      "begin" : 2102,
      "end" : 2103,
      "text" : ")",
      "whiteSpace" : false
    }, {
      "id" : "s12-t58",
      "begin" : 2103,
      "end" : 2104,
      "text" : ".",
      "whiteSpace" : false
    } ]
  }, {
    "id" : "s13",
    "begin" : 2105,
    "end" : 2160,
    "text" : "A decisão negativa foi tomada pelo STF por\runanimidade.",
    "tokens" : [ {
      "id" : "s13-t0",
      "begin" : 2105,
      "end" : 2106,
      "text" : "A",
      "whiteSpace" : false
    }, {
      "id" : "s13-t1",
      "begin" : 2107,
      "end" : 2114,
      "text" : "decisão",
      "whiteSpace" : false
    }, {
      "id" : "s13-t2",
      "begin" : 2115,
      "end" : 2123,
      "text" : "negativa",
      "whiteSpace" : false
    }, {
      "id" : "s13-t3",
      "begin" : 2124,
      "end" : 2127,
      "text" : "foi",
      "whiteSpace" : false
    }, {
      "id" : "s13-t4",
      "begin" : 2128,
      "end" : 2134,
      "text" : "tomada",
      "whiteSpace" : false
    }, {
      "id" : "s13-t5",
      "begin" : 2135,
      "end" : 2139,
      "text" : "pelo",
      "whiteSpace" : false
    }, {
      "id" : "s13-t6",
      "begin" : 2140,
      "end" : 2143,
      "text" : "STF",
      "whiteSpace" : false
    }, {
      "id" : "s13-t7",
      "begin" : 2144,
      "end" : 2147,
      "text" : "por",
      "whiteSpace" : false
    }, {
      "id" : "s13-t8",
      "begin" : 2148,
      "end" : 2159,
      "text" : "unanimidade",
      "whiteSpace" : false
    }, {
      "id" : "s13-t9",
      "begin" : 2159,
      "end" : 2160,
      "text" : ".",
      "whiteSpace" : false
    } ]
  }, {
    "id" : "s14",
    "begin" : 2161,
    "end" : 2207,
    "text" : "Castro Nunes deixou o STF em setembro de 1949.",
    "tokens" : [ {
      "id" : "s14-t0",
      "begin" : 2161,
      "end" : 2167,
      "text" : "Castro",
      "whiteSpace" : false
    }, {
      "id" : "s14-t1",
      "begin" : 2168,
      "end" : 2173,
      "text" : "Nunes",
      "whiteSpace" : false
    }, {
      "id" : "s14-t2",
      "begin" : 2174,
      "end" : 2180,
      "text" : "deixou",
      "whiteSpace" : false
    }, {
      "id" : "s14-t3",
      "begin" : 2181,
      "end" : 2182,
      "text" : "o",
      "whiteSpace" : false
    }, {
      "id" : "s14-t4",
      "begin" : 2183,
      "end" : 2186,
      "text" : "STF",
      "whiteSpace" : false
    }, {
      "id" : "s14-t5",
      "begin" : 2187,
      "end" : 2189,
      "text" : "em",
      "whiteSpace" : false
    }, {
      "id" : "s14-t6",
      "begin" : 2190,
      "end" : 2198,
      "text" : "setembro",
      "whiteSpace" : false
    }, {
      "id" : "s14-t7",
      "begin" : 2199,
      "end" : 2201,
      "text" : "de",
      "whiteSpace" : false
    }, {
      "id" : "s14-t8",
      "begin" : 2202,
      "end" : 2206,
      "text" : "1949",
      "whiteSpace" : false
    }, {
      "id" : "s14-t9",
      "begin" : 2206,
      "end" : 2207,
      "text" : ".",
      "whiteSpace" : false
    } ]
  }, {
    "id" : "s15",
    "begin" : 2209,
    "end" : 2315,
    "text" : "Jornalista, colaborou ainda na *Gazeta Judiciária*, em 1953, e no *Jornal\rdo Comércio*, do Rio de Janeiro.",
    "tokens" : [ {
      "id" : "s15-t0",
      "begin" : 2209,
      "end" : 2219,
      "text" : "Jornalista",
      "whiteSpace" : false
    }, {
      "id" : "s15-t1",
      "begin" : 2219,
      "end" : 2220,
      "text" : ",",
      "whiteSpace" : false
    }, {
      "id" : "s15-t2",
      "begin" : 2221,
      "end" : 2230,
      "text" : "colaborou",
      "whiteSpace" : false
    }, {
      "id" : "s15-t3",
      "begin" : 2231,
      "end" : 2236,
      "text" : "ainda",
      "whiteSpace" : false
    }, {
      "id" : "s15-t4",
      "begin" : 2237,
      "end" : 2239,
      "text" : "na",
      "whiteSpace" : false
    }, {
      "id" : "s15-t5",
      "begin" : 2240,
      "end" : 2247,
      "text" : "*Gazeta",
      "whiteSpace" : false
    }, {
      "id" : "s15-t6",
      "begin" : 2248,
      "end" : 2258,
      "text" : "Judiciária",
      "whiteSpace" : false
    }, {
      "id" : "s15-t7",
      "begin" : 2258,
      "end" : 2259,
      "text" : "*",
      "whiteSpace" : false
    }, {
      "id" : "s15-t8",
      "begin" : 2259,
      "end" : 2260,
      "text" : ",",
      "whiteSpace" : false
    }, {
      "id" : "s15-t9",
      "begin" : 2261,
      "end" : 2263,
      "text" : "em",
      "whiteSpace" : false
    }, {
      "id" : "s15-t10",
      "begin" : 2264,
      "end" : 2268,
      "text" : "1953",
      "whiteSpace" : false
    }, {
      "id" : "s15-t11",
      "begin" : 2268,
      "end" : 2269,
      "text" : ",",
      "whiteSpace" : false
    }, {
      "id" : "s15-t12",
      "begin" : 2270,
      "end" : 2271,
      "text" : "e",
      "whiteSpace" : false
    }, {
      "id" : "s15-t13",
      "begin" : 2272,
      "end" : 2274,
      "text" : "no",
      "whiteSpace" : false
    }, {
      "id" : "s15-t14",
      "begin" : 2275,
      "end" : 2282,
      "text" : "*Jornal",
      "whiteSpace" : false
    }, {
      "id" : "s15-t15",
      "begin" : 2283,
      "end" : 2285,
      "text" : "do",
      "whiteSpace" : false
    }, {
      "id" : "s15-t16",
      "begin" : 2286,
      "end" : 2294,
      "text" : "Comércio",
      "whiteSpace" : false
    }, {
      "id" : "s15-t17",
      "begin" : 2294,
      "end" : 2295,
      "text" : "*",
      "whiteSpace" : false
    }, {
      "id" : "s15-t18",
      "begin" : 2295,
      "end" : 2296,
      "text" : ",",
      "whiteSpace" : false
    }, {
      "id" : "s15-t19",
      "begin" : 2297,
      "end" : 2299,
      "text" : "do",
      "whiteSpace" : false
    }, {
      "id" : "s15-t20",
      "begin" : 2300,
      "end" : 2303,
      "text" : "Rio",
      "whiteSpace" : false
    }, {
      "id" : "s15-t21",
      "begin" : 2304,
      "end" : 2306,
      "text" : "de",
      "whiteSpace" : false
    }, {
      "id" : "s15-t22",
      "begin" : 2307,
      "end" : 2314,
      "text" : "Janeiro",
      "whiteSpace" : false
    }, {
      "id" : "s15-t23",
      "begin" : 2314,
      "end" : 2315,
      "text" : ".",
      "whiteSpace" : false
    } ]
  }, {
    "id" : "s16",
    "begin" : 2317,
    "end" : 2515,
    "text" : "Sócio da Academia Fluminense de Letras e do Instituto dos Advogados\rBrasileiros, integrou o conselho administrativo da Caixa Econômica\rFederal e o Conselho Penitenciário do Estado do Rio de Janeiro.",
    "tokens" : [ {
      "id" : "s16-t0",
      "begin" : 2317,
      "end" : 2322,
      "text" : "Sócio",
      "whiteSpace" : false
    }, {
      "id" : "s16-t1",
      "begin" : 2323,
      "end" : 2325,
      "text" : "da",
      "whiteSpace" : false
    }, {
      "id" : "s16-t2",
      "begin" : 2326,
      "end" : 2334,
      "text" : "Academia",
      "whiteSpace" : false
    }, {
      "id" : "s16-t3",
      "begin" : 2335,
      "end" : 2345,
      "text" : "Fluminense",
      "whiteSpace" : false
    }, {
      "id" : "s16-t4",
      "begin" : 2346,
      "end" : 2348,
      "text" : "de",
      "whiteSpace" : false
    }, {
      "id" : "s16-t5",
      "begin" : 2349,
      "end" : 2355,
      "text" : "Letras",
      "whiteSpace" : false
    }, {
      "id" : "s16-t6",
      "begin" : 2356,
      "end" : 2357,
      "text" : "e",
      "whiteSpace" : false
    }, {
      "id" : "s16-t7",
      "begin" : 2358,
      "end" : 2360,
      "text" : "do",
      "whiteSpace" : false
    }, {
      "id" : "s16-t8",
      "begin" : 2361,
      "end" : 2370,
      "text" : "Instituto",
      "whiteSpace" : false
    }, {
      "id" : "s16-t9",
      "begin" : 2371,
      "end" : 2374,
      "text" : "dos",
      "whiteSpace" : false
    }, {
      "id" : "s16-t10",
      "begin" : 2375,
      "end" : 2384,
      "text" : "Advogados",
      "whiteSpace" : false
    }, {
      "id" : "s16-t11",
      "begin" : 2385,
      "end" : 2396,
      "text" : "Brasileiros",
      "whiteSpace" : false
    }, {
      "id" : "s16-t12",
      "begin" : 2396,
      "end" : 2397,
      "text" : ",",
      "whiteSpace" : false
    }, {
      "id" : "s16-t13",
      "begin" : 2398,
      "end" : 2406,
      "text" : "integrou",
      "whiteSpace" : false
    }, {
      "id" : "s16-t14",
      "begin" : 2407,
      "end" : 2408,
      "text" : "o",
      "whiteSpace" : false
    }, {
      "id" : "s16-t15",
      "begin" : 2409,
      "end" : 2417,
      "text" : "conselho",
      "whiteSpace" : false
    }, {
      "id" : "s16-t16",
      "begin" : 2418,
      "end" : 2432,
      "text" : "administrativo",
      "whiteSpace" : false
    }, {
      "id" : "s16-t17",
      "begin" : 2433,
      "end" : 2435,
      "text" : "da",
      "whiteSpace" : false
    }, {
      "id" : "s16-t18",
      "begin" : 2436,
      "end" : 2441,
      "text" : "Caixa",
      "whiteSpace" : false
    }, {
      "id" : "s16-t19",
      "begin" : 2442,
      "end" : 2451,
      "text" : "Econômica",
      "whiteSpace" : false
    }, {
      "id" : "s16-t20",
      "begin" : 2452,
      "end" : 2459,
      "text" : "Federal",
      "whiteSpace" : false
    }, {
      "id" : "s16-t21",
      "begin" : 2460,
      "end" : 2461,
      "text" : "e",
      "whiteSpace" : false
    }, {
      "id" : "s16-t22",
      "begin" : 2462,
      "end" : 2463,
      "text" : "o",
      "whiteSpace" : false
    }, {
      "id" : "s16-t23",
      "begin" : 2464,
      "end" : 2472,
      "text" : "Conselho",
      "whiteSpace" : false
    }, {
      "id" : "s16-t24",
      "begin" : 2473,
      "end" : 2486,
      "text" : "Penitenciário",
      "whiteSpace" : false
    }, {
      "id" : "s16-t25",
      "begin" : 2487,
      "end" : 2489,
      "text" : "do",
      "whiteSpace" : false
    }, {
      "id" : "s16-t26",
      "begin" : 2490,
      "end" : 2496,
      "text" : "Estado",
      "whiteSpace" : false
    }, {
      "id" : "s16-t27",
      "begin" : 2497,
      "end" : 2499,
      "text" : "do",
      "whiteSpace" : false
    }, {
      "id" : "s16-t28",
      "begin" : 2500,
      "end" : 2503,
      "text" : "Rio",
      "whiteSpace" : false
    }, {
      "id" : "s16-t29",
      "begin" : 2504,
      "end" : 2506,
      "text" : "de",
      "whiteSpace" : false
    }, {
      "id" : "s16-t30",
      "begin" : 2507,
      "end" : 2514,
      "text" : "Janeiro",
      "whiteSpace" : false
    }, {
      "id" : "s16-t31",
      "begin" : 2514,
      "end" : 2515,
      "text" : ".",
      "whiteSpace" : false
    } ]
  }, {
    "id" : "s17",
    "begin" : 2517,
    "end" : 2572,
    "text" : "Faleceu no Rio de Janeiro no dia 5 de setembro de 1959.",
    "tokens" : [ {
      "id" : "s17-t0",
      "begin" : 2517,
      "end" : 2524,
      "text" : "Faleceu",
      "whiteSpace" : false
    }, {
      "id" : "s17-t1",
      "begin" : 2525,
      "end" : 2527,
      "text" : "no",
      "whiteSpace" : false
    }, {
      "id" : "s17-t2",
      "begin" : 2528,
      "end" : 2531,
      "text" : "Rio",
      "whiteSpace" : false
    }, {
      "id" : "s17-t3",
      "begin" : 2532,
      "end" : 2534,
      "text" : "de",
      "whiteSpace" : false
    }, {
      "id" : "s17-t4",
      "begin" : 2535,
      "end" : 2542,
      "text" : "Janeiro",
      "whiteSpace" : false
    }, {
      "id" : "s17-t5",
      "begin" : 2543,
      "end" : 2545,
      "text" : "no",
      "whiteSpace" : false
    }, {
      "id" : "s17-t6",
      "begin" : 2546,
      "end" : 2549,
      "text" : "dia",
      "whiteSpace" : false
    }, {
      "id" : "s17-t7",
      "begin" : 2550,
      "end" : 2551,
      "text" : "5",
      "whiteSpace" : false
    }, {
      "id" : "s17-t8",
      "begin" : 2552,
      "end" : 2554,
      "text" : "de",
      "whiteSpace" : false
    }, {
      "id" : "s17-t9",
      "begin" : 2555,
      "end" : 2563,
      "text" : "setembro",
      "whiteSpace" : false
    }, {
      "id" : "s17-t10",
      "begin" : 2564,
      "end" : 2566,
      "text" : "de",
      "whiteSpace" : false
    }, {
      "id" : "s17-t11",
      "begin" : 2567,
      "end" : 2571,
      "text" : "1959",
      "whiteSpace" : false
    }, {
      "id" : "s17-t12",
      "begin" : 2571,
      "end" : 2572,
      "text" : ".",
      "whiteSpace" : false
    } ]
  }, {
    "id" : "s18",
    "begin" : 2574,
    "end" : 3063,
    "text" : "Publicou *Do Estado federado e sua organização municipal* (1920), *As\rconstituições estaduais do Brasil comentadas e comparadas entre si e com\ra Constituição Federal* (1922), *A jornada revisionista* (1924), *Do mandado\rde segurança e de outros meios de defesa contra atos de poder público*\r(1937), *Teoria e prática do Poder Judiciário* (1943), *Soluções de direito\raplicado* (1953), *Alguns homens de meu tempo* (1957), *Bitributação e\rcompetência jurídica* e *Fazenda pública em juízo*.",
    "tokens" : [ {
      "id" : "s18-t0",
      "begin" : 2574,
      "end" : 2582,
      "text" : "Publicou",
      "whiteSpace" : false
    }, {
      "id" : "s18-t1",
      "begin" : 2583,
      "end" : 2584,
      "text" : "*",
      "whiteSpace" : false
    }, {
      "id" : "s18-t2",
      "begin" : 2584,
      "end" : 2586,
      "text" : "Do",
      "whiteSpace" : false
    }, {
      "id" : "s18-t3",
      "begin" : 2587,
      "end" : 2593,
      "text" : "Estado",
      "whiteSpace" : false
    }, {
      "id" : "s18-t4",
      "begin" : 2594,
      "end" : 2602,
      "text" : "federado",
      "whiteSpace" : false
    }, {
      "id" : "s18-t5",
      "begin" : 2603,
      "end" : 2604,
      "text" : "e",
      "whiteSpace" : false
    }, {
      "id" : "s18-t6",
      "begin" : 2605,
      "end" : 2608,
      "text" : "sua",
      "whiteSpace" : false
    }, {
      "id" : "s18-t7",
      "begin" : 2609,
      "end" : 2620,
      "text" : "organização",
      "whiteSpace" : false
    }, {
      "id" : "s18-t8",
      "begin" : 2621,
      "end" : 2630,
      "text" : "municipal",
      "whiteSpace" : false
    }, {
      "id" : "s18-t9",
      "begin" : 2630,
      "end" : 2631,
      "text" : "*",
      "whiteSpace" : false
    }, {
      "id" : "s18-t10",
      "begin" : 2632,
      "end" : 2633,
      "text" : "(",
      "whiteSpace" : false
    }, {
      "id" : "s18-t11",
      "begin" : 2633,
      "end" : 2637,
      "text" : "1920",
      "whiteSpace" : false
    }, {
      "id" : "s18-t12",
      "begin" : 2637,
      "end" : 2638,
      "text" : ")",
      "whiteSpace" : false
    }, {
      "id" : "s18-t13",
      "begin" : 2638,
      "end" : 2639,
      "text" : ",",
      "whiteSpace" : false
    }, {
      "id" : "s18-t14",
      "begin" : 2640,
      "end" : 2643,
      "text" : "*As",
      "whiteSpace" : false
    }, {
      "id" : "s18-t15",
      "begin" : 2644,
      "end" : 2657,
      "text" : "constituições",
      "whiteSpace" : false
    }, {
      "id" : "s18-t16",
      "begin" : 2658,
      "end" : 2667,
      "text" : "estaduais",
      "whiteSpace" : false
    }, {
      "id" : "s18-t17",
      "begin" : 2668,
      "end" : 2670,
      "text" : "do",
      "whiteSpace" : false
    }, {
      "id" : "s18-t18",
      "begin" : 2671,
      "end" : 2677,
      "text" : "Brasil",
      "whiteSpace" : false
    }, {
      "id" : "s18-t19",
      "begin" : 2678,
      "end" : 2688,
      "text" : "comentadas",
      "whiteSpace" : false
    }, {
      "id" : "s18-t20",
      "begin" : 2689,
      "end" : 2690,
      "text" : "e",
      "whiteSpace" : false
    }, {
      "id" : "s18-t21",
      "begin" : 2691,
      "end" : 2701,
      "text" : "comparadas",
      "whiteSpace" : false
    }, {
      "id" : "s18-t22",
      "begin" : 2702,
      "end" : 2707,
      "text" : "entre",
      "whiteSpace" : false
    }, {
      "id" : "s18-t23",
      "begin" : 2708,
      "end" : 2710,
      "text" : "si",
      "whiteSpace" : false
    }, {
      "id" : "s18-t24",
      "begin" : 2711,
      "end" : 2712,
      "text" : "e",
      "whiteSpace" : false
    }, {
      "id" : "s18-t25",
      "begin" : 2713,
      "end" : 2716,
      "text" : "com",
      "whiteSpace" : false
    }, {
      "id" : "s18-t26",
      "begin" : 2717,
      "end" : 2718,
      "text" : "a",
      "whiteSpace" : false
    }, {
      "id" : "s18-t27",
      "begin" : 2719,
      "end" : 2731,
      "text" : "Constituição",
      "whiteSpace" : false
    }, {
      "id" : "s18-t28",
      "begin" : 2732,
      "end" : 2739,
      "text" : "Federal",
      "whiteSpace" : false
    }, {
      "id" : "s18-t29",
      "begin" : 2739,
      "end" : 2740,
      "text" : "*",
      "whiteSpace" : false
    }, {
      "id" : "s18-t30",
      "begin" : 2741,
      "end" : 2742,
      "text" : "(",
      "whiteSpace" : false
    }, {
      "id" : "s18-t31",
      "begin" : 2742,
      "end" : 2746,
      "text" : "1922",
      "whiteSpace" : false
    }, {
      "id" : "s18-t32",
      "begin" : 2746,
      "end" : 2747,
      "text" : ")",
      "whiteSpace" : false
    }, {
      "id" : "s18-t33",
      "begin" : 2747,
      "end" : 2748,
      "text" : ",",
      "whiteSpace" : false
    }, {
      "id" : "s18-t34",
      "begin" : 2749,
      "end" : 2751,
      "text" : "*A",
      "whiteSpace" : false
    }, {
      "id" : "s18-t35",
      "begin" : 2752,
      "end" : 2759,
      "text" : "jornada",
      "whiteSpace" : false
    }, {
      "id" : "s18-t36",
      "begin" : 2760,
      "end" : 2772,
      "text" : "revisionista",
      "whiteSpace" : false
    }, {
      "id" : "s18-t37",
      "begin" : 2772,
      "end" : 2773,
      "text" : "*",
      "whiteSpace" : false
    }, {
      "id" : "s18-t38",
      "begin" : 2774,
      "end" : 2775,
      "text" : "(",
      "whiteSpace" : false
    }, {
      "id" : "s18-t39",
      "begin" : 2775,
      "end" : 2779,
      "text" : "1924",
      "whiteSpace" : false
    }, {
      "id" : "s18-t40",
      "begin" : 2779,
      "end" : 2780,
      "text" : ")",
      "whiteSpace" : false
    }, {
      "id" : "s18-t41",
      "begin" : 2780,
      "end" : 2781,
      "text" : ",",
      "whiteSpace" : false
    }, {
      "id" : "s18-t42",
      "begin" : 2782,
      "end" : 2783,
      "text" : "*",
      "whiteSpace" : false
    }, {
      "id" : "s18-t43",
      "begin" : 2783,
      "end" : 2785,
      "text" : "Do",
      "whiteSpace" : false
    }, {
      "id" : "s18-t44",
      "begin" : 2786,
      "end" : 2793,
      "text" : "mandado",
      "whiteSpace" : false
    }, {
      "id" : "s18-t45",
      "begin" : 2794,
      "end" : 2796,
      "text" : "de",
      "whiteSpace" : false
    }, {
      "id" : "s18-t46",
      "begin" : 2797,
      "end" : 2806,
      "text" : "segurança",
      "whiteSpace" : false
    }, {
      "id" : "s18-t47",
      "begin" : 2807,
      "end" : 2808,
      "text" : "e",
      "whiteSpace" : false
    }, {
      "id" : "s18-t48",
      "begin" : 2809,
      "end" : 2811,
      "text" : "de",
      "whiteSpace" : false
    }, {
      "id" : "s18-t49",
      "begin" : 2812,
      "end" : 2818,
      "text" : "outros",
      "whiteSpace" : false
    }, {
      "id" : "s18-t50",
      "begin" : 2819,
      "end" : 2824,
      "text" : "meios",
      "whiteSpace" : false
    }, {
      "id" : "s18-t51",
      "begin" : 2825,
      "end" : 2827,
      "text" : "de",
      "whiteSpace" : false
    }, {
      "id" : "s18-t52",
      "begin" : 2828,
      "end" : 2834,
      "text" : "defesa",
      "whiteSpace" : false
    }, {
      "id" : "s18-t53",
      "begin" : 2835,
      "end" : 2841,
      "text" : "contra",
      "whiteSpace" : false
    }, {
      "id" : "s18-t54",
      "begin" : 2842,
      "end" : 2846,
      "text" : "atos",
      "whiteSpace" : false
    }, {
      "id" : "s18-t55",
      "begin" : 2847,
      "end" : 2849,
      "text" : "de",
      "whiteSpace" : false
    }, {
      "id" : "s18-t56",
      "begin" : 2850,
      "end" : 2855,
      "text" : "poder",
      "whiteSpace" : false
    }, {
      "id" : "s18-t57",
      "begin" : 2856,
      "end" : 2863,
      "text" : "público",
      "whiteSpace" : false
    }, {
      "id" : "s18-t58",
      "begin" : 2863,
      "end" : 2864,
      "text" : "*",
      "whiteSpace" : false
    }, {
      "id" : "s18-t59",
      "begin" : 2865,
      "end" : 2866,
      "text" : "(",
      "whiteSpace" : false
    }, {
      "id" : "s18-t60",
      "begin" : 2866,
      "end" : 2870,
      "text" : "1937",
      "whiteSpace" : false
    }, {
      "id" : "s18-t61",
      "begin" : 2870,
      "end" : 2871,
      "text" : ")",
      "whiteSpace" : false
    }, {
      "id" : "s18-t62",
      "begin" : 2871,
      "end" : 2872,
      "text" : ",",
      "whiteSpace" : false
    }, {
      "id" : "s18-t63",
      "begin" : 2873,
      "end" : 2880,
      "text" : "*Teoria",
      "whiteSpace" : false
    }, {
      "id" : "s18-t64",
      "begin" : 2881,
      "end" : 2882,
      "text" : "e",
      "whiteSpace" : false
    }, {
      "id" : "s18-t65",
      "begin" : 2883,
      "end" : 2890,
      "text" : "prática",
      "whiteSpace" : false
    }, {
      "id" : "s18-t66",
      "begin" : 2891,
      "end" : 2893,
      "text" : "do",
      "whiteSpace" : false
    }, {
      "id" : "s18-t67",
      "begin" : 2894,
      "end" : 2899,
      "text" : "Poder",
      "whiteSpace" : false
    }, {
      "id" : "s18-t68",
      "begin" : 2900,
      "end" : 2910,
      "text" : "Judiciário",
      "whiteSpace" : false
    }, {
      "id" : "s18-t69",
      "begin" : 2910,
      "end" : 2911,
      "text" : "*",
      "whiteSpace" : false
    }, {
      "id" : "s18-t70",
      "begin" : 2912,
      "end" : 2913,
      "text" : "(",
      "whiteSpace" : false
    }, {
      "id" : "s18-t71",
      "begin" : 2913,
      "end" : 2917,
      "text" : "1943",
      "whiteSpace" : false
    }, {
      "id" : "s18-t72",
      "begin" : 2917,
      "end" : 2918,
      "text" : ")",
      "whiteSpace" : false
    }, {
      "id" : "s18-t73",
      "begin" : 2918,
      "end" : 2919,
      "text" : ",",
      "whiteSpace" : false
    }, {
      "id" : "s18-t74",
      "begin" : 2920,
      "end" : 2929,
      "text" : "*Soluções",
      "whiteSpace" : false
    }, {
      "id" : "s18-t75",
      "begin" : 2930,
      "end" : 2932,
      "text" : "de",
      "whiteSpace" : false
    }, {
      "id" : "s18-t76",
      "begin" : 2933,
      "end" : 2940,
      "text" : "direito",
      "whiteSpace" : false
    }, {
      "id" : "s18-t77",
      "begin" : 2941,
      "end" : 2949,
      "text" : "aplicado",
      "whiteSpace" : false
    }, {
      "id" : "s18-t78",
      "begin" : 2949,
      "end" : 2950,
      "text" : "*",
      "whiteSpace" : false
    }, {
      "id" : "s18-t79",
      "begin" : 2951,
      "end" : 2952,
      "text" : "(",
      "whiteSpace" : false
    }, {
      "id" : "s18-t80",
      "begin" : 2952,
      "end" : 2956,
      "text" : "1953",
      "whiteSpace" : false
    }, {
      "id" : "s18-t81",
      "begin" : 2956,
      "end" : 2957,
      "text" : ")",
      "whiteSpace" : false
    }, {
      "id" : "s18-t82",
      "begin" : 2957,
      "end" : 2958,
      "text" : ",",
      "whiteSpace" : false
    }, {
      "id" : "s18-t83",
      "begin" : 2959,
      "end" : 2966,
      "text" : "*Alguns",
      "whiteSpace" : false
    }, {
      "id" : "s18-t84",
      "begin" : 2967,
      "end" : 2973,
      "text" : "homens",
      "whiteSpace" : false
    }, {
      "id" : "s18-t85",
      "begin" : 2974,
      "end" : 2976,
      "text" : "de",
      "whiteSpace" : false
    }, {
      "id" : "s18-t86",
      "begin" : 2977,
      "end" : 2980,
      "text" : "meu",
      "whiteSpace" : false
    }, {
      "id" : "s18-t87",
      "begin" : 2981,
      "end" : 2986,
      "text" : "tempo",
      "whiteSpace" : false
    }, {
      "id" : "s18-t88",
      "begin" : 2986,
      "end" : 2987,
      "text" : "*",
      "whiteSpace" : false
    }, {
      "id" : "s18-t89",
      "begin" : 2988,
      "end" : 2989,
      "text" : "(",
      "whiteSpace" : false
    }, {
      "id" : "s18-t90",
      "begin" : 2989,
      "end" : 2993,
      "text" : "1957",
      "whiteSpace" : false
    }, {
      "id" : "s18-t91",
      "begin" : 2993,
      "end" : 2994,
      "text" : ")",
      "whiteSpace" : false
    }, {
      "id" : "s18-t92",
      "begin" : 2994,
      "end" : 2995,
      "text" : ",",
      "whiteSpace" : false
    }, {
      "id" : "s18-t93",
      "begin" : 2996,
      "end" : 3009,
      "text" : "*Bitributação",
      "whiteSpace" : false
    }, {
      "id" : "s18-t94",
      "begin" : 3010,
      "end" : 3011,
      "text" : "e",
      "whiteSpace" : false
    }, {
      "id" : "s18-t95",
      "begin" : 3012,
      "end" : 3023,
      "text" : "competência",
      "whiteSpace" : false
    }, {
      "id" : "s18-t96",
      "begin" : 3024,
      "end" : 3032,
      "text" : "jurídica",
      "whiteSpace" : false
    }, {
      "id" : "s18-t97",
      "begin" : 3032,
      "end" : 3033,
      "text" : "*",
      "whiteSpace" : false
    }, {
      "id" : "s18-t98",
      "begin" : 3034,
      "end" : 3035,
      "text" : "e",
      "whiteSpace" : false
    }, {
      "id" : "s18-t99",
      "begin" : 3036,
      "end" : 3044,
      "text" : "*Fazenda",
      "whiteSpace" : false
    }, {
      "id" : "s18-t100",
      "begin" : 3045,
      "end" : 3052,
      "text" : "pública",
      "whiteSpace" : false
    }, {
      "id" : "s18-t101",
      "begin" : 3053,
      "end" : 3055,
      "text" : "em",
      "whiteSpace" : false
    }, {
      "id" : "s18-t102",
      "begin" : 3056,
      "end" : 3061,
      "text" : "juízo",
      "whiteSpace" : false
    }, {
      "id" : "s18-t103",
      "begin" : 3061,
      "end" : 3062,
      "text" : "*",
      "whiteSpace" : false
    }, {
      "id" : "s18-t104",
      "begin" : 3062,
      "end" : 3063,
      "text" : ".",
      "whiteSpace" : false
    } ]
  } ],
  "mentions" : [ {
    "id" : "s3-m0",
    "source" : "PREANNOTATION",
    "properties" : {
      "SIRE_ENTITY_SUBTYPE" : "NONE",
      "SIRE_MENTION_CLASS" : "SPC",
      "SIRE_MENTION_TYPE" : "NONE",
      "SIRE_MENTION_ROLE" : "ORGANIZACAO"
    },
    "type" : "ORGANIZACAO",
    "begin" : 202,
    "end" : 218,
    "inCoref" : false
  }, {
    "id" : "s8-m0",
    "source" : "PREANNOTATION",
    "properties" : {
      "SIRE_ENTITY_SUBTYPE" : "NONE",
      "SIRE_MENTION_CLASS" : "SPC",
      "SIRE_MENTION_TYPE" : "NONE",
      "SIRE_MENTION_ROLE" : "ORGANIZACAO"
    },
    "type" : "ORGANIZACAO",
    "begin" : 461,
    "end" : 466,
    "inCoref" : false
  }, {
    "id" : "s19-m0",
    "source" : "PREANNOTATION",
    "properties" : {
      "SIRE_ENTITY_SUBTYPE" : "NONE",
      "SIRE_MENTION_CLASS" : "SPC",
      "SIRE_MENTION_TYPE" : "NONE",
      "SIRE_MENTION_ROLE" : "ORGANIZACAO"
    },
    "type" : "ORGANIZACAO",
    "begin" : 951,
    "end" : 974,
    "inCoref" : false
  }, {
    "id" : "s21-m0",
    "source" : "PREANNOTATION",
    "properties" : {
      "SIRE_ENTITY_SUBTYPE" : "NONE",
      "SIRE_MENTION_CLASS" : "SPC",
      "SIRE_MENTION_TYPE" : "NONE",
      "SIRE_MENTION_ROLE" : "ORGANIZACAO"
    },
    "type" : "ORGANIZACAO",
    "begin" : 1067,
    "end" : 1078,
    "inCoref" : false
  }, {
    "id" : "s22-m0",
    "source" : "PREANNOTATION",
    "properties" : {
      "SIRE_ENTITY_SUBTYPE" : "NONE",
      "SIRE_MENTION_CLASS" : "SPC",
      "SIRE_MENTION_TYPE" : "NONE",
      "SIRE_MENTION_ROLE" : "EVENTO_PROCESSO"
    },
    "type" : "EVENTO_PROCESSO",
    "begin" : 1088,
    "end" : 1105,
    "inCoref" : false
  }, {
    "id" : "s25-m0",
    "source" : "PREANNOTATION",
    "properties" : {
      "SIRE_ENTITY_SUBTYPE" : "NONE",
      "SIRE_MENTION_CLASS" : "SPC",
      "SIRE_MENTION_TYPE" : "NONE",
      "SIRE_MENTION_ROLE" : "LEI_CONSTITUICAO"
    },
    "type" : "LEI_CONSTITUICAO",
    "begin" : 1284,
    "end" : 1296,
    "inCoref" : false
  }, {
    "id" : "s26-m0",
    "source" : "PREANNOTATION",
    "properties" : {
      "SIRE_ENTITY_SUBTYPE" : "NONE",
      "SIRE_MENTION_CLASS" : "SPC",
      "SIRE_MENTION_TYPE" : "NONE",
      "SIRE_MENTION_ROLE" : "ORGANIZACAO"
    },
    "type" : "ORGANIZACAO",
    "begin" : 1331,
    "end" : 1343,
    "inCoref" : false
  }, {
    "id" : "s34-m0",
    "source" : "PREANNOTATION",
    "properties" : {
      "SIRE_ENTITY_SUBTYPE" : "NONE",
      "SIRE_MENTION_CLASS" : "SPC",
      "SIRE_MENTION_TYPE" : "NONE",
      "SIRE_MENTION_ROLE" : "ORGANIZACAO"
    },
    "type" : "ORGANIZACAO",
    "begin" : 1672,
    "end" : 1675,
    "inCoref" : false
  }, {
    "id" : "s35-m0",
    "source" : "PREANNOTATION",
    "properties" : {
      "SIRE_ENTITY_SUBTYPE" : "NONE",
      "SIRE_MENTION_CLASS" : "SPC",
      "SIRE_MENTION_TYPE" : "NONE",
      "SIRE_MENTION_ROLE" : "ORGANIZACAO"
    },
    "type" : "ORGANIZACAO",
    "begin" : 1747,
    "end" : 1777,
    "inCoref" : false
  }, {
    "id" : "s37-m0",
    "source" : "PREANNOTATION",
    "properties" : {
      "SIRE_ENTITY_SUBTYPE" : "NONE",
      "SIRE_MENTION_CLASS" : "SPC",
      "SIRE_MENTION_TYPE" : "NONE",
      "SIRE_MENTION_ROLE" : "ORGANIZACAO"
    },
    "type" : "ORGANIZACAO",
    "begin" : 1847,
    "end" : 1852,
    "inCoref" : false
  }, {
    "id" : "s42-m0",
    "source" : "PREANNOTATION",
    "properties" : {
      "SIRE_ENTITY_SUBTYPE" : "NONE",
      "SIRE_MENTION_CLASS" : "SPC",
      "SIRE_MENTION_TYPE" : "NONE",
      "SIRE_MENTION_ROLE" : "ORGANIZACAO"
    },
    "type" : "ORGANIZACAO",
    "begin" : 2140,
    "end" : 2143,
    "inCoref" : false
  }, {
    "id" : "s44-m0",
    "source" : "PREANNOTATION",
    "properties" : {
      "SIRE_ENTITY_SUBTYPE" : "NONE",
      "SIRE_MENTION_CLASS" : "SPC",
      "SIRE_MENTION_TYPE" : "NONE",
      "SIRE_MENTION_ROLE" : "ORGANIZACAO"
    },
    "type" : "ORGANIZACAO",
    "begin" : 2183,
    "end" : 2186,
    "inCoref" : false
  }, {
    "id" : "s47-m0",
    "source" : "PREANNOTATION",
    "properties" : {
      "SIRE_ENTITY_SUBTYPE" : "NONE",
      "SIRE_MENTION_CLASS" : "SPC",
      "SIRE_MENTION_TYPE" : "NONE",
      "SIRE_MENTION_ROLE" : "ORGANIZACAO"
    },
    "type" : "ORGANIZACAO",
    "begin" : 2326,
    "end" : 2355,
    "inCoref" : false
  }, {
    "id" : "s47-m1",
    "source" : "PREANNOTATION",
    "properties" : {
      "SIRE_ENTITY_SUBTYPE" : "NONE",
      "SIRE_MENTION_CLASS" : "SPC",
      "SIRE_MENTION_TYPE" : "NONE",
      "SIRE_MENTION_ROLE" : "ORGANIZACAO"
    },
    "type" : "ORGANIZACAO",
    "begin" : 2361,
    "end" : 2384,
    "inCoref" : false
  }, {
    "id" : "s48-m0",
    "source" : "PREANNOTATION",
    "properties" : {
      "SIRE_ENTITY_SUBTYPE" : "NONE",
      "SIRE_MENTION_CLASS" : "SPC",
      "SIRE_MENTION_TYPE" : "NONE",
      "SIRE_MENTION_ROLE" : "ORGANIZACAO"
    },
    "type" : "ORGANIZACAO",
    "begin" : 2409,
    "end" : 2417,
    "inCoref" : false
  }, {
    "id" : "s48-m1",
    "source" : "PREANNOTATION",
    "properties" : {
      "SIRE_ENTITY_SUBTYPE" : "NONE",
      "SIRE_MENTION_CLASS" : "SPC",
      "SIRE_MENTION_TYPE" : "NONE",
      "SIRE_MENTION_ROLE" : "ORGANIZACAO"
    },
    "type" : "ORGANIZACAO",
    "begin" : 2436,
    "end" : 2441,
    "inCoref" : false
  }, {
    "id" : "s49-m0",
    "source" : "PREANNOTATION",
    "properties" : {
      "SIRE_ENTITY_SUBTYPE" : "NONE",
      "SIRE_MENTION_CLASS" : "SPC",
      "SIRE_MENTION_TYPE" : "NONE",
      "SIRE_MENTION_ROLE" : "ORGANIZACAO"
    },
    "type" : "ORGANIZACAO",
    "begin" : 2464,
    "end" : 2496,
    "inCoref" : false
  }, {
    "id" : "s53-m0",
    "source" : "PREANNOTATION",
    "properties" : {
      "SIRE_ENTITY_SUBTYPE" : "NONE",
      "SIRE_MENTION_CLASS" : "SPC",
      "SIRE_MENTION_TYPE" : "NONE",
      "SIRE_MENTION_ROLE" : "LEI_CONSTITUICAO"
    },
    "type" : "LEI_CONSTITUICAO",
    "begin" : 2719,
    "end" : 2739,
    "inCoref" : false
  }, {
    "id" : "s55-m0",
    "source" : "PREANNOTATION",
    "properties" : {
      "SIRE_ENTITY_SUBTYPE" : "NONE",
      "SIRE_MENTION_CLASS" : "SPC",
      "SIRE_MENTION_TYPE" : "NONE",
      "SIRE_MENTION_ROLE" : "ORGANIZACAO"
    },
    "type" : "ORGANIZACAO",
    "begin" : 2900,
    "end" : 2910,
    "inCoref" : false
  } ],
  "relations" : [ ],
  "corefs" : [ ],
  "typeResolved" : true,
  "userResolved" : true
}